Workbook

Sheet GDP
A1: Years | B1: Values (millions of R$) | K1: Table 2
A2: 2002 | B2: 98847.211 | K2: GDP,price and volume indexes and % changes, Rio Grande do Sul — 2002-21
A3: 2003 | B3: 119325.4
A4: 2004 | B4: 131192.21 | K4: YEARS | L4: VALUE (Millions of R$) | N4: Real Change (Volume Change) | Q4: Price Index
A5: 2005 | B5: 136362.77 | N5: (2002=100) | O5: Change % | Q5: (2000=100) | R5: Change %
A6: 2006 | B6: 147622.6 | K6: 2002 | L6: 98847.211 | N6: 100 | O6: - | Q6: 100 | R6: -
A7: 2007 | B7: 168009.75 | H7: =L6*1000000*(1+O7/100) -> 1.0085418e+11 | I7: =LN(H7) -> 25.336942 | K7: 2003 | L7: 119325.4 | N7: 102.03038 | O7: 2.0303764 | Q7: 118.31478 | R7: 18.314776
A8: 2008 | B8: 190229.82 | H8: =H7*(1+O8/100) -> 1.0415853e+11 | I8: =LN(H8) -> 25.36918 | K8: 2004 | L8: 131192.21 | N8: 105.37326 | O8: 3.2763598 | Q8: 125.95436 | R8: 6.4569991
A9: 2009 | B9: 204344.94 | H9: =H8*(1+O9/100) -> 1.0130377e+11 | I9: =LN(H9) -> 25.341389 | K9: 2005 | L9: 136362.77 | N9: 102.4852 | O9: -2.7407852 | Q9: 134.6078 | R9: 6.8702968
A10: 2010 | B10: 241249.16 | H10: =H9*(1+O10/100) -> 1.0541777e+11 | I10: =LN(H10) -> 25.381197 | K10: 2006 | L10: 147622.6 | N10: 106.64719 | O10: 4.0610593 | Q10: 140.03578 | R10: 4.0324426
A11: 2011 | B11: 265056.42 | H11: =H10*(1+O11/100) -> 1.1252254e+11 | I11: =LN(H11) -> 25.446419 | K11: 2007 | L11: 168009.75 | N11: 113.83481 | O11: 6.7396282 | Q11: 149.31209 | R11: 6.6242421
A12: 2012 | B12: 287587.02 | H12: =H11*(1+O12/100) -> 1.1575489e+11 | I12: =LN(H12) -> 25.474741 | K12: 2008 | L12: 190229.82 | N12: 117.10486 | O12: 2.8726278 | Q12: 164.33847 | R12: 10.063743
A13: 2013 | B13: 332292.73 | H13: =H12*(1+O13/100) -> 1.1448234e+11 | I13: =LN(H13) -> 25.463686 | K13: 2009 | L13: 204344.94 | N13: 115.81747 | O13: -1.0993489 | Q13: 178.49473 | R13: 8.6140819
A14: 2014 | B14: 357816.42 | H14: =H13*(1+O14/100) -> 1.223621e+11 | I14: =LN(H14) -> 25.530251 | K14: 2010 | L14: 241249.16 | N14: 123.78913 | O14: 6.8829486 | Q14: 197.16004 | R14: 10.457066 | U14: =Q25/Q14 -> 2.1965459
A15: 2015 | B15: 381992.6 | H15: =H14*(1+O15/100) -> 1.2796661e+11 | I15: =LN(H15) -> 25.575035 | K15: 2011 | L15: 265056.42 | N15: 129.459 | O15: 4.5802667 | Q15: 207.12935 | R15: 5.0564593
A16: 2016 | B16: 408789.53 | H16: =H15*(1+O16/100) -> 1.2526667e+11 | I16: =LN(H16) -> 25.553711 | K16: 2012 | L16: 287587.02 | N16: 126.72757 | O16: -2.1098808 | Q16: 229.57984 | R16: 10.838873
A17: 2017 | B17: 423270.05 | H17: =H16*(1+O17/100) -> 1.3594959e+11 | I17: =LN(H17) -> 25.63555 | K17: 2013 | L17: 332292.73 | N17: 137.53508 | O17: 8.5281403 | Q17: 244.42349 | R17: 6.4655727
A18: 2018 | B18: 457293.96 | H18: =H17*(1+O18/100) -> 1.3557226e+11 | I18: =LN(H18) -> 25.632771 | K18: 2014 | L18: 357816.42 | N18: 137.15335 | O18: -0.27754584 | Q18: 263.9304 | R18: 7.9807845
A19: 2019 | B19: 482464.18 | H19: =H18*(1+O19/100) -> 1.2932673e+11 | I19: =LN(H19) -> 25.585608 | K19: 2015 | L19: 381992.6 | N19: 130.83498 | O19: -4.6067966 | Q19: 295.37019 | R19: 11.912152
A20: 2020 | B20: 470941.85 | H20: =H19*(1+O20/100) -> 1.2620005e+11 | I20: =LN(H20) -> 25.561134 | K20: 2016 | L20: 408789.53 | N20: 127.67184 | O20: -2.4176545 | Q20: 323.92184 | R20: 9.6663927
A21: 2021 (1) | B21: 584601.62 | H21: =H20*(1+O21/100) -> 1.2846739e+11 | I21: =LN(H21) -> 25.578941 | K21: 2017 | L21: 423270.05 | N21: 129.96562 | O21: 1.7966232 | Q21: 329.47664 | R21: 1.7148594
A22: 2022 (1) | B22: 594054.64 | H22: =H21*(1+O22/100) -> 1.3099006e+11 | I22: =LN(H22) -> 25.598387 | K22: 2018 | L22: 457293.96 | N22: 132.51771 | O22: 1.963663 | Q22: 349.10585 | R22: 5.9576938
A23: Source: SPGG-RS/DEE. | H23: =H22*(1+O23/100) -> 1.3237366e+11 | I23: =LN(H23) -> 25.608895 | K23: 2019 | L23: 482464.18 | N23: 133.91745 | O23: 1.0562662 | Q23: 364.47143 | R23: 4.4014095
A24: IBGE/Diretoria de Pesquisas/Coordenação de Contas Nacionais. | H24: =H23*(1+O24/100) -> 1.2282647e+11 | I24: =LN(H24) -> 25.534038 | K24: 2020 | L24: 470941.85 | N24: 124.25892 | O24: -7.2123027 | Q24: 383.42047 | R24: 5.1990485
A25: (1) Preliminary estimatives. | H25: =H24*(1+O25/100) -> 1.3422362e+11 | I25: =LN(H25) -> 25.622773 | K25: 2021 | L25: 581283.68 | N25: 135.78899 | O25: 9.2790675 | Q25: 433.07106 | R25: 12.949384
K26: Source: SPGG-RS/DEE.
K27: IBGE, em parceria com os Órgãos Estaduais de Estatística, Secretarias de Governo e Superintendência da Zona Franca de Manaus - SUFRAMA.

Sheet Goverment Expenditure
B1: Cities | C1: State | F1: Central Goverment | I1: RS Nominal GDP | J1: GL | K1: GC | L1: IGL | M1: IGC/GC
A2: Year | B2: Expenditure | C2: Expenditure | D2: GL+IGL | F2: Total expenditure without debt and transfers | G2: Expenditure in RS (GC + IGC)
A3: 2010 | B3: 1.7368542e+10 | C3: 1.9355181e+10 | D3: =B3+C3 -> 3.6723723e+10 | F3: 6.5827165e+11 | G3: =F3*0.063 -> 4.1471114e+10 | I3: 2.4124916e+11 | J3: =(B3+C3)/I3 -> 0.15222321 | K3: =G3/I3 -> 0.17190159 | L3: =D33/D3 -> 0.11167504 | M3: =G33/G3 -> 0.070503207
A4: 2011 | B4: 1.9866493e+10 | C4: 2.0953285e+10 | D4: =B4+C4 -> 4.0819778e+10 | F4: 7.1827038e+11 | G4: =F4*0.063 -> 4.5251034e+10 | I4: 2.6505642e+11 | J4: =(B4+C4)/I4 -> 0.15400411 | K4: =G4/I4 -> 0.17072227 | L4: =D34/D4 -> 0.083313419 | M4: =G34/G4 -> 0.063446128
A5: 2012 | B5: 2.2884206e+10 | C5: 2.3104363e+10 | D5: =B5+C5 -> 4.5988568e+10 | F5: 8.1559429e+11 | G5: =F5*0.063 -> 5.138244e+10 | I5: 2.8758702e+11 | J5: =(B5+C5)/I5 -> 0.15991184 | K5: =G5/I5 -> 0.17866745 | L5: =D35/D5 -> 0.085066453 | M5: =G35/G5 -> 0.06323377
A6: 2013 | B6: 2.3563372e+10 | C6: 2.6539106e+10 | D6: =B6+C6 -> 5.0102478e+10 | F6: 9.2317937e+11 | G6: =F6*0.063 -> 5.81603e+10 | I6: 3.3229273e+11 | J6: =(B6+C6)/I6 -> 0.15077814 | K6: =G6/I6 -> 0.1750273 | L6: =D36/D6 -> 0.068615324 | M6: =G36/G6 -> 0.069393877
A7: 2014 | B7: 2.5502193e+10 | C7: 3.0349249e+10 | D7: =B7+C7 -> 5.5851442e+10 | F7: 9.9747265e+11 | G7: =F7*0.063 -> 6.2840777e+10 | I7: 3.5781642e+11 | J7: =(B7+C7)/I7 -> 0.15608965 | K7: =G7/I7 -> 0.17562295 | L7: =D37/D7 -> 0.072735037 | M7: =G37/G7 -> 0.076284942
A8: 2015 | B8: 2.799268e+10 | C8: 3.2121887e+10 | D8: =B8+C8 -> 6.0114567e+10 | F8: 1.0552754e+12 | G8: =F8*0.063 -> 6.648235e+10 | I8: 3.819926e+11 | J8: =(B8+C8)/I8 -> 0.15737103 | K8: =G8/I8 -> 0.17404094 | L8: =D38/D8 -> 0.050632867 | M8: =G38/G8 -> 0.050827052
A9: 2016 | B9: 2.8915852e+10 | C9: 3.3627075e+10 | D9: =B9+C9 -> 6.2542927e+10 | F9: 1.1554465e+12 | G9: =F9*0.063 -> 7.2793127e+10 | I9: 4.0878953e+11 | J9: =(B9+C9)/I9 -> 0.15299542 | K9: =G9/I9 -> 0.17806994 | L9: =D39/D9 -> 0.04736227 | M9: =G39/G9 -> 0.055665609
A10: 2017 | B10: 3.0121373e+10 | C10: 3.5776093e+10 | D10: =B10+C10 -> 6.5897465e+10 | F10: 1.243663e+12 | G10: =F10*0.063 -> 7.835077e+10 | I10: 4.2327005e+11 | J10: =(B10+C10)/I10 -> 0.15568658 | K10: =G10/I10 -> 0.18510823 | L10: =D40/D10 -> 0.038947157 | M10: =G40/G10 -> 0.037083948
A11: 2018 | B11: 3.3831687e+10 | C11: 3.9010731e+10 | D11: =B11+C11 -> 7.2842418e+10 | F11: 1.2967884e+12 | G11: =F11*0.063 -> 8.169767e+10 | I11: 4.5729396e+11 | J11: =(B11+C11)/I11 -> 0.15929014 | K11: =G11/I11 -> 0.1786546 | L11: =D41/D11 -> 0.049936426 | M11: =G41/G11 -> 0.04048292
A12: 2019 | B12: 3.5981665e+10 | C12: 3.9808416e+10 | D12: =B12+C12 -> 7.5790081e+10 | F12: 1.3577899e+12 | G12: =F12*0.063 -> 8.5540767e+10 | I12: 4.8246418e+11 | J12: =(B12+C12)/I12 -> 0.15708955 | K12: =G12/I12 -> 0.17729973 | L12: =D42/D12 -> 0.043284166 | M12: =G42/G12 -> 0.041680494
A13: 2020 | B13: 3.950338e+10 | C13: 4.1365888e+10 | D13: =B13+C13 -> 8.0869267e+10 | F13: 1.7624162e+12 | G13: =F13*0.063 -> 1.1103222e+11 | I13: 4.7094185e+11 | J13: =(B13+C13)/I13 -> 0.17171816 | K13: =G13/I13 -> 0.23576631 | L13: =D43/D13 -> 0.051943577 | M13: =G43/G13 -> 0.059523113
A14: 2021 | B14: 4.4155193e+10 | C14: 4.4963461e+10 | D14: =B14+C14 -> 8.9118654e+10 | F14: 1.5639211e+12 | G14: =F14*0.063 -> 9.8527029e+10 | I14: 5.81283e+11 | J14: =(B14+C14)/I14 -> 0.15331371 | K14: =G14/I14 -> 0.16949924 | L14: =D44/D14 -> 0.064722372 | M14: =G44/G14 -> 0.036337022
F16: https://atlassocioeconomico.rs.gov.br/participacao-do-pib-estadual
F17: 6,3% of RS share in Brazil's GDP -> primary expenditure of Central Government in RS is 6,3% of total primary expenditure
A22: CAGE | B22: empenhado rs | C22: encargos | D22: efetivo
A23: 2010 | B23: 2.8780981e+10 | C23: 9.4258002e+09 | D23: =B23-C23 -> 1.9355181e+10
A24: 2011 | B24: 3.0104315e+10 | C24: 9.1510294e+09 | D24: =B24-C24 -> 2.0953285e+10
A25: 2012 | B25: 3.3232383e+10 | C25: 1.012802e+10 | D25: =B25-C25 -> 2.3104363e+10
A26: CAGE | B26: liquidado rs | C26: encargos | D26: efetivo
A27: 2010 | B27: 2.8280088e+10 | C27: 9.3121126e+09 | D27: =B27-C27 -> 1.8967975e+10
A28: 2011 | B28: 2.9640688e+10 | C28: 9.0012484e+09 | D28: =B28-C28 -> 2.063944e+10
A29: 2012 | B29: 3.2749598e+10 | C29: 1.0099038e+10 | D29: =B29-C29 -> 2.265056e+10
B32: Cities Investment | C32: State Investment | D32: Total Local Investment | F32: Total Central Public Investment | G32: Central Public Investment in RS
A33: 2010 | B33: 2.2366429e+09 | C33: 1.8644802e+09 | D33: =B33+C33 -> 4.1011231e+09 | E33: =D33/(B3+C3) -> 0.11167504 | F33: 4.6410262e+10 | G33: =F33*0.063 -> 2.9238465e+09
A34: 2011 | B34: 2.5187982e+09 | C34: 8.8203706e+08 | D34: =B34+C34 -> 3.4008353e+09 | E34: =D34/(B4+C4) -> 0.083313419 | F34: 4.5571474e+10 | G34: =F34*0.063 -> 2.8710029e+09
A35: 2012 | B35: 2.9313286e+09 | C35: 9.8075573e+08 | D35: =B35+C35 -> 3.9120844e+09 | E35: =D35/(B5+C5) -> 0.085066453 | F35: 5.1573102e+10 | G35: =F35*0.063 -> 3.2491054e+09
A36: 2013 | B36: 2.1038205e+09 | C36: 1.3339773e+09 | D36: =B36+C36 -> 3.4377978e+09 | E36: =D36/(B6+C6) -> 0.068615324 | F36: 6.4062996e+10 | G36: =F36*0.063 -> 4.0359687e+09
A37: 2014 | B37: 2.6102914e+09 | C37: 1.4520652e+09 | D37: =B37+C37 -> 4.0623567e+09 | E37: =D37/(B7+C7) -> 0.072735037 | F37: 7.6092144e+10 | G37: =F37*0.063 -> 4.793805e+09
A38: 2015 | B38: 2.3855766e+09 | C38: 6.5819624e+08 | D38: =B38+C38 -> 3.0437729e+09 | E38: =D38/(B8+C8) -> 0.050632867 | F38: 5.3636538e+10 | G38: =F38*0.063 -> 3.3791019e+09
A39: 2016 | B39: 2.1210087e+09 | C39: 841166257 | D39: =B39+C39 -> 2.962175e+09 | E39: =D39/(B9+C9) -> 0.04736227 | F39: 6.431863e+10 | G39: =F39*0.063 -> 4.0520737e+09
A40: 2017 | B40: 1.5304133e+09 | C40: 1.0361057e+09 | D40: =B40+C40 -> 2.5665189e+09 | E40: =D40/(B10+C10) -> 0.038947157 | F40: 4.6119935e+10 | G40: =F40*0.063 -> 2.9055559e+09
A41: 2018 | B41: 1.9955198e+09 | C41: 1.6419702e+09 | D41: =B41+C41 -> 3.63749e+09 | E41: =D41/(B11+C11) -> 0.049936426 | F41: 5.2497781e+10 | G41: =F41*0.063 -> 3.3073602e+09
A42: 2019 | B42: 2.4430861e+09 | C42: 8.3742437e+08 | D42: =B42+C42 -> 3.2805105e+09 | E42: =D42/(B12+C12) -> 0.043284166 | F42: 5.6593356e+10 | G42: =F42*0.063 -> 3.5653814e+09
A43: 2020 | B43: 3.3363051e+09 | C43: 8.6433389e+08 | D43: =B43+C43 -> 4.200639e+09 | E43: =D43/(B13+C13) -> 0.051943577 | F43: 1.049045e+11 | G43: =F43*0.063 -> 6.6089834e+09
A44: 2021 | B44: 3.4673214e+09 | C44: 2.3006493e+09 | D44: =B44+C44 -> 5.7679707e+09 | E44: =D44/(B14+C14) -> 0.064722372 | F44: 5.6828236e+10 | G44: =F44*0.063 -> 3.5801788e+09
A46: 2010 | B46: 2011 | C46: 2012
A47: Cities investment | B47: Cities investment | C47: Cities investment
A48: 2921074.7 | B48: 2579257.3 | C48: 1589613.9
A49: 2302149.4 | B49: 2501634.8 | C49: 2621584.5
A50: 4094592.5 | B50: 3223796.2 | C50: 5770209.1
A51: 1623325.7 | B51: 2023850.6 | C51: 1452358.6
A52: 1011014.7 | B52: 1527126.9 | C52: 880156.56
A53: 10036818 | B53: 4719132.9 | C53: 6813795.4
A54: 1535730.1 | B54: 1924154.9 | C54: 1408396.5
A55: 2251436.6 | B55: 923907.21 | C55: 1004206.9
A56: 3936921 | B56: 3823774.9 | C56: 2513753.8
A57: 2081414.7 | B57: 3010163.7 | C57: 2418941
A58: 991005.41 | B58: 1914615.3 | C58: 1534580.3
A59: 12123892 | B59: 6741223.7 | C59: 12203652
... A540: 2339067.6 | B540: 886326.91 | C540: 4117262.9
B541: 2379743.2 | C541: 5334502.4
B542: 7496267
A545: =SUM(A48:A540) -> 2.2366429e+09 | B545: =SUM(B48:B542) -> 2.5187982e+09 | C545: =SUM(C48:C541) -> 2.9313286e+09

Sheet Goverment Revenues
B1: Municípios | G1: RS
B2: ISSQN | C2: IPTU | D2: IRRF + CONTR. PREV. | G2: ICMS | H2: IPVA | I2: IRRF | J2: CONTR. PREV. | M2: Transf. União | O2: GL | R2: TR/GL | S2: CONSUMO/GL | T2: RENDA/GL
A3: 2010 | G3: 1.7283265e+10 | H3: 1.4582327e+09 | I3: 1.7101787e+09 | J3: 1.3920337e+09 | M3: 5926882957 | O3: 3.6723723e+10
A4: 2011 | G4: 1.9040822e+10 | H4: 1.6313574e+09 | I4: 1.0699622e+09 | J4: 1.6502039e+09 | M4: 7098573823 | O4: 4.0819778e+10
A5: 2012 | G5: 2.0730511e+10 | H5: 1.8416612e+09 | I5: 1.1859901e+09 | J5: 1.7783069e+09 | M5: 7123523054 | O5: 4.5988568e+10
A6: 2013 | G6: 2.3497323e+10 | H6: 1.9731983e+09 | I6: 1.4118679e+09 | J6: 2.1728516e+09 | M6: 7481644974 | O6: 5.0102478e+10
A7: 2014 | G7: 2.5224531e+10 | H7: 2.1591144e+09 | I7: 1.707707e+09 | J7: 2.5597842e+09 | M7: 8410816941 | O7: 5.5851442e+10
A8: 2015 | G8: 2.6167838e+10 | H8: 2.3356418e+09 | I8: 1.7243994e+09 | J8: 2.6948939e+09 | M8: 8786060273 | O8: 6.0114567e+10
A9: 2016 | G9: 2.9605777e+10 | H9: 2.3389905e+09 | I9: 2.2343784e+09 | J9: 3.1244337e+09 | M9: 9959769604 | O9: 6.2542927e+10
A10: 2017 | G10: 3.1213974e+10 | H10: 2.32059e+09 | I10: 2.6350527e+09 | J10: 3.1575627e+09 | M10: 9680425966 | O10: 6.5897465e+10
A11: 2018 | B11: 2.7185904e+09 | C11: 3.2218561e+09 | D11: 2.5471638e+09 | G11: 3.3553455e+10 | H11: 2.8791767e+09 | I11: 2.7426882e+09 | J11: 3.5977904e+09 | M11: 10255405079 | O11: 7.2842418e+10 | R11: =M11/O11 -> 0.14078892 | S11: =(SUM(G11:H11)+SUM(B11:C11))/O11 -> 0.58170884 | T11: =(SUM(I11:J11)+SUM(D11))/O11 -> 0.12201191
A12: 2019 | G12: 3.6528755e+10 | H12: 3.0723666e+09 | I12: 3.2279749e+09 | J12: 3.7092731e+09 | M12: 15113156721 | O12: 7.5790081e+10
A13: 2020 | G13: 3.6370809e+10 | H13: 3.2182748e+09 | I13: 3.2820196e+09 | J13: 4.3947963e+09 | M13: 13766175656 | O13: 8.0869267e+10
A14: 2021 | G14: 4.7560079e+10 | H14: 3.9325986e+09 | I14: 3.2483007e+09 | J14: 4.5883617e+09 | M14: 17433933335 | O14: 8.9118654e+10
A15: 2022
S16: =85/70 -> 1.2142857
A18: Arrecadação União
A19: https://dados.gov.br/dados/conjuntos-dados/resultado-da-arrecadacao | S19: =S16*S11 -> 0.70636073 | T19: =S16*T11 -> 0.14815732
G20: 6.64 | H20: 42.3
A22: Averages | B22: Consumption Tax | C22: Income Tax | D22: Firms Tax | E22: Expenditure in RS
A23: UNIÃO | B23: 2.2790039e+09 | C23: 4.3740413e+10 | D23: 1.1110924e+10 | E23: 65000000000 | H23: =G20/(G20+H20) -> 0.13567634
A25: ICMS+IPVA | B25: 27500000000 | C25: 4600000000 | D25: 0
A26: ISSQN+IPTU | B26: 1300000000 | C26: 634000000
B27: 28800000000 | C27: 5234000000
B29: tht_c | C29: tht_w
B30: =B23/(B23+B27) -> 0.073329374 | C30: =C23/(C23+C27) -> 0.89312787 | E30: =5.234/42 -> 0.12461905
B32: 373000000000
A34: Receita para GL | B34: 0.077211796 | C34: 0.014032172
A35: Receita para GC | B35: 0.00610993 | C35: 0.11726652 | D35: 0.029788001
B38: theta_c | C38: 0.075
B39: theta_w | C39: 0.85
B44: 2.850348e+10 | C44: 3.1944768e+10 | D44: 3.3534564e+10 | E44: 3.6432632e+10
B45: 2015 | C45: 2016 | D45: 2017 | E45: 2018
B49: 3.819926e+11 | C49: 4.0878953e+11 | D49: 4.2327005e+11 | E49: 4.5729396e+11
B51: =B44/B49 -> 0.074617885 | C51: =C44/C49 -> 0.07814478 | D51: =D44/D49 -> 0.079227349 | E51: =E44/E49 -> 0.079670048
B53: =AVERAGE(B49:E49) -> 4.1783653e+11
B54: =AVERAGE(B44:E44) -> 3.2603861e+10
B56: =B54/B53 -> 0.078030182

Sheet Series
A1: Ano | B1: PIB | C1: GL + IGL | D1: GC + IGC | E1: π_POA | F1: Selic | G1: Juro Real | H1: Remuneração | I1: Salários | J1: Contribuição social | K1: IGL | L1: IGC | M1: Transferências da União
A2: 2006 | E2: 0.0268
A3: 2007 | E3: 0.0371
A4: 2008 | E4: 0.0657
A5: 2009 | E5: 0.0372
A6: 2010 | B6: 2.4124916e+11 | C6: 3.6723723e+10 | D6: 3.8220762e+10 | E6: 0.0514 | F6: 0.10355639 | G6: =(1+F6)/(1+E6) -> 1.0496066 | H6: 9.6993646e+10 | I6: 76589.311 | J6: 20404.335 | K6: 4.1011231e+09 | L6: ='Goverment Expenditure'!F33*0.063 -> 2.9238465e+09 | M6: 5926882957
A7: 2011 | B7: 2.6505642e+11 | C7: 4.0819778e+10 | D7: 4.1611195e+10 | E7: 0.0653 | F7: 0.12407487 | G7: =(1+F7)/(1+E7) -> 1.0551721 | H7: 1.1301526e+11 | I7: 88859.732 | J7: 24155.532 | K7: 3.4008353e+09 | L7: ='Goverment Expenditure'!F34*0.063 -> 2.8710029e+09 | M7: 7098573823
A8: 2012 | B8: 2.8758702e+11 | C8: 4.5988568e+10 | D8: 4.6644739e+10 | E8: 0.0556 | F8: 0.08984348 | G8: =(1+F8)/(1+E8) -> 1.0324398 | H8: 1.2322767e+11 | I8: 97462.667 | J8: 25765.007 | K8: 3.9120844e+09 | L8: ='Goverment Expenditure'!F35*0.063 -> 3.2491054e+09 | M8: 7123523054
A9: 2013 | B9: 3.3229273e+11 | C9: 5.0102478e+10 | D9: 5.2889252e+10 | E9: 0.0579 | F9: 0.086076769 | G9: =(1+F9)/(1+E9) -> 1.0266346 | H9: 1.4124514e+11 | I9: 111947.73 | J9: 29297.409 | K9: 3.4377978e+09 | L9: ='Goverment Expenditure'!F36*0.063 -> 4.0359687e+09 | M9: 7481644974
A10: 2014 | B10: 3.5781642e+11 | C10: 5.5851442e+10 | D10: 5.8517018e+10 | E10: 0.0677 | F10: 0.11523655 | G10: =(1+F10)/(1+E10) -> 1.0445224 | H10: 1.5388199e+11 | I10: 122844.39 | J10: 31037.606 | K10: 4.0623567e+09 | L10: ='Goverment Expenditure'!F37*0.063 -> 4.793805e+09 | M10: 8410816941
A11: 2015 | B11: 3.819926e+11 | C11: 6.0114567e+10 | D11: 6.2856104e+10 | E11: 0.1122 | F11: 0.14329025 | G11: =(1+F11)/(1+E11) -> 1.0279538 | H11: 1.6141045e+11 | I11: 128958 | J11: 32452.448 | K11: 3.0437729e+09 | L11: ='Goverment Expenditure'!F38*0.063 -> 3.3791019e+09 | M11: 8786060273
A12: 2016 | B12: 4.0878953e+11 | C12: 6.2542927e+10 | D12: 6.9615004e+10 | E12: 0.0695 | F12: 0.15138213 | G12: =(1+F12)/(1+E12) -> 1.0765611 | H12: 1.7045027e+11 | I12: 135948.6 | J12: 34501.667 | K12: 2.962175e+09 | L12: ='Goverment Expenditure'!F39*0.063 -> 4.0520737e+09 | M12: 9959769604
A13: 2017 | B13: 4.2327005e+11 | C13: 6.5897465e+10 | D13: 7.4628687e+10 | E13: 0.0252 | F13: 0.10654852 | G13: =(1+F13)/(1+E13) -> 1.0793489 | H13: 1.7878412e+11 | I13: 141938.07 | J13: 36846.045 | K13: 2.5665189e+09 | L13: ='Goverment Expenditure'!F40*0.063 -> 2.9055559e+09 | M13: 9680425966
A14: 2018 | B14: 4.5729396e+11 | C14: 7.2842418e+10 | D14: 7.8149805e+10 | E14: 0.0462 | F14: 0.067840374 | G14: =(1+F14)/(1+E14) -> 1.0206847 | H14: 1.868295e+11 | I14: 148191.47 | J14: 38638.03 | K14: 3.63749e+09 | L14: ='Goverment Expenditure'!F41*0.063 -> 3.3073602e+09 | M14: 10255405079
A15: 2019 | B15: 4.8246418e+11 | C15: 7.5790081e+10 | D15: 8.1775377e+10 | E15: 0.0408 | F15: 0.062082222 | G15: =(1+F15)/(1+E15) -> 1.0204479 | H15: 1.9777212e+11 | I15: 156181.54 | J15: 41590.576 | K15: 3.2805105e+09 | L15: ='Goverment Expenditure'!F42*0.063 -> 3.5653814e+09 | M15: 15113156721
A16: 2020 | B16: 4.7094185e+11 | C16: 8.0869267e+10 | D16: 1.0635369e+11 | E16: 0.0422 | F16: 0.029293873 | G16: =(1+F16)/(1+E16) -> 0.98761646 | H16: 1.9078626e+11 | I16: 151515.46 | J16: 39270.805 | K16: 4.200639e+09 | L16: ='Goverment Expenditure'!F43*0.063 -> 6.6089834e+09 | M16: 13766175656
A17: 2021 | B17: 5.8128368e+11 | C17: 8.9118654e+10 | D17: 9.338537e+10 | E17: 0.1099 | F17: 0.046146759 | G17: =(1+F17)/(1+E17) -> 0.94255947 | H17: 2.1442366e+11 | I17: 169747.43 | J17: 44676.231 | K17: 5.7679707e+09 | L17: ='Goverment Expenditure'!F44*0.063 -> 3.5801788e+09 | M17: 17433933335
A18: 2022 | E18: 0.044
B20: SERIES WITH CONSTANT PRICES (2010) | K20: PARÂMETROS DE PROPORÇÕES DAS CONTAS NACIONAIS (STEADY-STATES)
B21: GDP | C21: GL + IGL | D21: GC + IGC | E21: π_POA | F21: Índice π_POA | G21: W (Total) | H21: IGL | I21: IGC | J21: TR | K21: GL/Y | L21: GC/Y | M21: IGL/Y | N21: IGC/Y | O21: W/Y | P21: IGL/GL | Q21: IGC/GC | R21: W_TR/GL | S21: W_TR/GC | U21: tht_c | V21: 0.135
A22: 2010 | B22: 2.4124916e+11 | C22: 3.6723723e+10 | D22: 3.8220762e+10 | E22: 0.0514 | F22: =1+E22 -> 1.0514 | G22: =H6 -> 9.6993646e+10 | H22: 4.1011231e+09 | I22: 2.9238465e+09 | J22: 5926882957 | K22: =(C22-H22)/$B22 -> 0.13522368 | L22: =(D22-I22)/$B22 -> 0.14630897 | M22: =H22/$B22 -> 0.016999533 | N22: =I22/$B22 -> 0.012119613 | O22: =G22/$B22 -> 0.40204759 | P22: =H22/C22 -> 0.11167504 | Q22: =I22/D22 -> 0.076498906 | R22: =J22/C22 -> 0.16139113 | S22: =J22/D22 -> 0.15506972 | U22: tht_w | V22: 0.9
A23: 2011 | B23: =B22*(1+GDP!O15/100) -> 2.5229902e+11 | C23: =(C7/C6)/(1+$E23)*C6 -> 3.8317636e+10 | D23: =(D7/D6)/(1+$E23)*D22 -> 3.9060541e+10 | E23: 0.0653 | F23: =1+E23 -> 1.0653 | G23: =(H7/H6)/(1+E23)*G22 -> 1.0608774e+11 | H23: =(K7/H22)/(1+E23)*H22 -> 3.1923733e+09 | I23: =(L7/I22)/(1+E23)*I22 -> 2.6950182e+09 | J23: =(M7/M6)/(1+E23)*J22 -> 6.6634505e+09 | K23: =(C23-H23)/$B23 -> 0.13922077 | L23: =(D23-I23)/$B23 -> 0.1441366 | M23: =H23/$B23 -> 0.012653134 | N23: =I23/$B23 -> 0.010681842 | O23: =G23/$B23 -> 0.42048414 | P23: =H23/C23 -> 0.083313419 | Q23: =I23/D23 -> 0.068995926 | R23: =J23/C23 -> 0.17390035 | S23: =J23/D23 -> 0.17059289 | U23: tht_f | V23: 1
A24: 2012 | B24: =B23*(1+GDP!O16/100) -> 2.4697581e+11 | C24: =(C8/C7)/(1+E24)*C23 -> 4.0895788e+10 | D24: =(D8/D7)/(1+$E24)*D23 -> 4.1479294e+10 | E24: 0.0556 | F24: =1+E24 -> 1.0556 | G24: =(H8/H7)/(1+E24)*G23 -> 1.0958142e+11 | H24: =(K8/H23)/(1+E24)*H23 -> 3.7060291e+09 | I24: =(L8/I23)/(1+E24)*I23 -> 3.0779703e+09 | J24: =(M8/M7)/(1+E24)*J23 -> 6.3346631e+09 | K24: =(C24-H24)/$B24 -> 0.15058057 | L24: =(D24-I24)/$B24 -> 0.15548617 | M24: =H24/$B24 -> 0.015005636 | N24: =I24/$B24 -> 0.012462639 | O24: =G24/$B24 -> 0.44369294 | P24: =H24/C24 -> 0.090621292 | Q24: =I24/D24 -> 0.074204982 | R24: =J24/C24 -> 0.15489769 | S24: =J24/D24 -> 0.15271868
A25: 2013 | B25: =B24*(1+GDP!O17/100) -> 2.6803825e+11 | C25: =(C9/C8)/(1+E25)*C24 -> 4.2115628e+10 | D25: =(D9/D8)/(1+$E25)*D24 -> 4.4458162e+10 | E25: 0.0579 | F25: =1+E25 -> 1.0579 | G25: =(H9/H8)/(1+E25)*G24 -> 1.1872921e+11 | H25: =(K9/H24)/(1+E25)*H24 -> 3.2496434e+09 | I25: =(L9/I24)/(1+E25)*I24 -> 3.8150758e+09 | J25: =(M9/M8)/(1+E25)*J24 -> 6.2889939e+09 | K25: =(C25-H25)/$B25 -> 0.14500163 | L25: =(D25-I25)/$B25 -> 0.15163166 | M25: =H25/$B25 -> 0.012123805 | N25: =I25/$B25 -> 0.014233326 | O25: =G25/$B25 -> 0.44295621 | P25: =H25/C25 -> 0.077160037 | Q25: =I25/D25 -> 0.085812722 | R25: =J25/C25 -> 0.14932685 | S25: =J25/D25 -> 0.1414587 | U25: w_br | W25: 0.12
A26: 2014 | B26: =B25*(1+GDP!O18/100) -> 2.6729433e+11 | C26: =(C10/C9)/(1+E26)*C25 -> 4.3971291e+10 | D26: =(D10/D9)/(1+$E26)*D25 -> 4.6069874e+10 | E26: 0.0677 | F26: =1+E26 -> 1.0677 | G26: =(H10/H9)/(1+E26)*G25 -> 1.2114978e+11 | H26: =(K10/H25)/(1+E26)*H25 -> 3.8047735e+09 | I26: =(L10/I25)/(1+E26)*I25 -> 4.4898427e+09 | J26: =(M10/M9)/(1+E26)*J25 -> 6.6217535e+09 | K26: =(C26-H26)/$B26 -> 0.15027075 | L26: =(D26-I26)/$B26 -> 0.15555897 | M26: =H26/$B26 -> 0.014234397 | N26: =I26/$B26 -> 0.016797374 | O26: =G26/$B26 -> 0.45324487 | P26: =H26/C26 -> 0.086528582 | Q26: =I26/D26 -> 0.097457239 | R26: =J26/C26 -> 0.15059266 | S26: =J26/D26 -> 0.14373283 | U26: w_gcc | W26: 0.1
A27: 2015 | B27: =B26*(1+GDP!O19/100) -> 2.5498062e+11 | C27: =(C11/C10)/(1+E27)*C26 -> 4.2553145e+10 | D27: =(D11/D10)/(1+$E27)*D26 -> 4.449379e+10 | E27: 0.1122 | F27: =1+E27 -> 1.1122 | G27: =(H11/H10)/(1+E27)*G26 -> 1.142572e+11 | H27: =(K11/H26)/(1+E27)*H26 -> 2.7367136e+09 | I27: =(L11/I26)/(1+E27)*I26 -> 3.0382142e+09 | J27: =(M11/M10)/(1+E27)*J26 -> 6.2193661e+09 | K27: =(C27-H27)/$B27 -> 0.15615474 | L27: =(D27-I27)/$B27 -> 0.16258324 | M27: =H27/$B27 -> 0.010733026 | N27: =I27/$B27 -> 0.011915471 | O27: =G27/$B27 -> 0.44810152 | P27: =H27/C27 -> 0.06431284 | Q27: =I27/D27 -> 0.068284006 | R27: =J27/C27 -> 0.14615526 | S27: =J27/D27 -> 0.13978054 | U27: w_gwc | W27: 0.5
A28: 2016 | B28: =B27*(1+GDP!O20/100) -> 2.4881607e+11 | C28: =(C12/C11)/(1+E28)*C27 -> 4.139514e+10 | D28: =(D12/D11)/(1+$E28)*D27 -> 4.6075919e+10 | E28: 0.0695 | F28: =1+E28 -> 1.0695 | G28: =(H12/H11)/(1+E28)*G27 -> 1.1281552e+11 | H28: =(K12/H27)/(1+E28)*H27 -> 2.7696821e+09 | I28: =(L12/I27)/(1+E28)*I27 -> 3.7887552e+09 | J28: =(M12/M11)/(1+E28)*J27 -> 6.5920493e+09 | K28: =(C28-H28)/$B28 -> 0.15523699 | L28: =(D28-I28)/$B28 -> 0.16995351 | M28: =H28/$B28 -> 0.011131444 | N28: =I28/$B28 -> 0.015227132 | O28: =G28/$B28 -> 0.45340929 | P28: =H28/C28 -> 0.066908388 | Q28: =I28/D28 -> 0.082228533 | R28: =J28/C28 -> 0.15924694 | S28: =J28/D28 -> 0.1430693 | U28: w_gf | W28: 0.43
A29: 2017 | B29: =B28*(1+GDP!O21/100) -> 2.5328636e+11 | C29: =(C13/C12)/(1+E29)*C28 -> 4.2543309e+10 | D29: =(D13/D12)/(1+$E29)*D28 -> 4.8180173e+10 | E29: 0.0252 | F29: =1+E29 -> 1.0252 | G29: =(H13/H12)/(1+E29)*G28 -> 1.1542277e+11 | H29: =(K13/H28)/(1+E29)*H28 -> 2.5034324e+09 | I29: =(L13/I28)/(1+E29)*I28 -> 2.8341357e+09 | J29: =(M13/M12)/(1+E29)*J28 -> 6.2496691e+09 | K29: =(C29-H29)/$B29 -> 0.15808146 | L29: =(D29-I29)/$B29 -> 0.17903072 | M29: =H29/$B29 -> 0.009883803 | N29: =I29/$B29 -> 0.011189453 | O29: =G29/$B29 -> 0.45570069 | P29: =H29/C29 -> 0.058844329 | Q29: =I29/D29 -> 0.058823692 | R29: =J29/C29 -> 0.14690134 | S29: =J29/D29 -> 0.12971454
A30: 2018 | B30: =B29*(1+GDP!O22/100) -> 2.5826005e+11 | C30: =(C14/C13)/(1+E30)*C29 -> 4.4950258e+10 | D30: =(D14/D13)/(1+$E30)*D29 -> 4.8225389e+10 | E30: 0.0462 | F30: =1+E30 -> 1.0462 | G30: =(H14/H13)/(1+E30)*G29 -> 1.1529044e+11 | H30: =(K14/H29)/(1+E30)*H29 -> 3.4768592e+09 | I30: =(L14/I29)/(1+E30)*I29 -> 3.1613078e+09 | J30: =(M14/M13)/(1+E30)*J29 -> 6.3284982e+09 | K30: =(C30-H30)/$B30 -> 0.16058775 | L30: =(D30-I30)/$B30 -> 0.17449111 | M30: =H30/$B30 -> 0.013462629 | N30: =I30/$B30 -> 0.012240793 | O30: =G30/$B30 -> 0.44641221 | P30: =H30/C30 -> 0.077349036 | Q30: =I30/D30 -> 0.06555277 | R30: =J30/C30 -> 0.14078892 | S30: =J30/D30 -> 0.13122752 | U30: w_gc | W30: 0.7
A31: 2019 | B31: =B30*(1+GDP!O23/100) -> 2.6098796e+11 | C31: =(C15/C14)/(1+E31)*C30 -> 4.4935847e+10 | D31: =(D15/D14)/(1+$E31)*D30 -> 4.8484521e+10 | E31: 0.0408 | F31: =1+E31 -> 1.0408 | G31: =(H15/H14)/(1+E31)*G30 -> 1.1725885e+11 | H31: =(K15/H30)/(1+E31)*H30 -> 3.1519124e+09 | I31: =(L15/I30)/(1+E31)*I30 -> 3.4256163e+09 | J31: =(M15/M14)/(1+E31)*J30 -> 8.9605722e+09 | K31: =(C31-H31)/$B31 -> 0.16009909 | L31: =(D31-I31)/$B31 -> 0.17264745 | M31: =H31/$B31 -> 0.01207685 | N31: =I31/$B31 -> 0.013125572 | O31: =G31/$B31 -> 0.44928834 | P31: =H31/C31 -> 0.070142496 | Q31: =I31/D31 -> 0.070653813 | R31: =J31/C31 -> 0.19940811 | S31: =J31/D31 -> 0.18481305 | U31: w_gw | W31: 0.14
A32: 2020 | B32: =B31*(1+GDP!O24/100) -> 2.4216472e+11 | C32: =(C16/C15)/(1+E32)*C31 -> 4.6005843e+10 | D32: =(D16/D15)/(1+$E32)*D31 -> 6.0503716e+10 | E32: 0.0422 | F32: =1+E32 -> 1.0422 | G32: =(H16/H15)/(1+E32)*G31 -> 1.0853669e+11 | H32: =(K16/H31)/(1+E32)*H31 -> 4.0305498e+09 | I32: =(L16/I31)/(1+E32)*I31 -> 6.3413772e+09 | J32: =(M16/M15)/(1+E32)*J31 -> 7.8314611e+09 | K32: =(C32-H32)/$B32 -> 0.17333365 | L32: =(D32-I32)/$B32 -> 0.22365908 | M32: =H32/$B32 -> 0.016643836 | N32: =I32/$B32 -> 0.026186214 | O32: =G32/$B32 -> 0.44819367 | P32: =H32/C32 -> 0.087609519 | Q32: =I32/D32 -> 0.10480972 | R32: =J32/C32 -> 0.17022753 | S32: =J32/D32 -> 0.12943769 | U32: w_tr | W32: 0.16
A33: 2021 | B33: =B32*(1+GDP!O25/100) -> 2.6463535e+11 | C33: =(C17/C16)/(1+E33)*C32 -> 4.5678755e+10 | D33: =(D17/D16)/(1+$E33)*D32 -> 4.7865707e+10 | E33: 0.1099 | F33: =1+E33 -> 1.1099 | G33: =(H17/H16)/(1+E33)*G32 -> 1.0990522e+11 | H33: =(K17/H32)/(1+E33)*H32 -> 5.1968382e+09 | I33: =(L17/I32)/(1+E33)*I32 -> 3.2256769e+09 | J33: =(M17/M16)/(1+E33)*J32 -> 8.9359559e+09 | K33: =(C33-H33)/$B33 -> 0.15297245 | L33: =(D33-I33)/$B33 -> 0.16868506 | M33: =H33/$B33 -> 0.019637733 | N33: =I33/$B33 -> 0.012189139 | O33: =G33/$B33 -> 0.41530818 | P33: =H33/C33 -> 0.11376926 | Q33: =I33/D33 -> 0.067390145 | R33: =J33/C33 -> 0.19562608 | S33: =J33/D33 -> 0.18668806 | U33: w_trc | W33: 0.15
A34: Média | B34: =AVERAGE(B22:B33) -> 2.5491564e+11 | C34: =AVERAGE(C22:C33) -> 4.2507197e+10 | D34: =AVERAGE(D22:D33) -> 4.6093154e+10 | E34: =AVERAGE(E22:E33) -> 0.061991667 | F34: =AVERAGE(F22:F33) -> 1.0619917 | G34: =AVERAGE(G22:G33) -> 1.1216904e+11 | H34: =AVERAGE(H22:H33) -> 3.4933275e+09 | I34: =AVERAGE(I22:I33) -> 3.5680697e+09 | ... S34: =AVERAGE(S22:S33) -> 0.15069196
B36: NATURAL LOG
B37: Y | C37: GL | D37: IGL | E37: GC | F37: IGC | G37: W | H37: π_POA | I37: Ac | J37: Ad
A38: 2010 | B38: =LN(B22) -> 26.209096 | C38: =LN(C22-H22) -> 24.208271 | D38: =LN(H22) -> 22.134527 | E38: =LN(D22-I22) -> 24.287061 | F38: =LN(I22) -> 21.796166 | G38: =LN(G22) -> 25.297911 | H38: =LN(F22) -> 0.050122609
A39: 2011 | B39: =LN(B23) -> 26.253881 | C39: =LN(C23-H23) -> 24.282186 | D39: =LN(H23) -> 21.88403 | E39: =LN(D23-I23) -> 24.316887 | F39: =LN(I23) -> 21.714671 | G39: =LN(G23) -> 25.387532 | H39: =LN(F23) -> 0.06325645 | I39: =LN(Ac!B19) -> 4.6051702 | J39: =LN(Ad!B20) -> 4.6051702
A40: 2012 | B40: =LN(B24) -> 26.232556 | C40: =LN(C24-H24) -> 24.339299 | D40: =LN(H24) -> 22.033227 | E40: =LN(D24-I24) -> 24.371358 | F40: =LN(I24) -> 21.847536 | G40: =LN(G24) -> 25.419934 | H40: =LN(F24) -> 0.054109326 | I40: =LN(Ac!B20) -> 4.5628726 | J40: =LN(Ad!B21) -> 4.6344867
A41: 2013 | B41: =LN(B25) -> 26.314396 | C41: =LN(C25-H25) -> 24.383385 | D41: =LN(H25) -> 21.901811 | E41: =LN(D25-I25) -> 24.428095 | F41: =LN(I25) -> 22.062226 | G41: =LN(G25) -> 25.500111 | H41: =LN(F25) -> 0.056285811 | I41: =LN(Ac!B21) -> 4.6090941 | J41: =LN(Ad!B22) -> 4.6906201
A42: 2014 | B42: =LN(B26) -> 26.311616 | C42: =LN(C26-H26) -> 24.4163 | D42: =LN(H26) -> 22.059522 | E42: =LN(D26-I26) -> 24.450886 | F42: =LN(I26) -> 22.225084 | G42: =LN(G26) -> 25.520293 | H42: =LN(F26) -> 0.065506802 | I42: =LN(Ac!B22) -> 4.5918212 | J42: =LN(Ad!B23) -> 4.6754933
A43: 2015 | B43: =LN(B27) -> 26.264453 | C43: =LN(C27-H27) -> 24.407546 | D43: =LN(H27) -> 21.730024 | E43: =LN(D27-I27) -> 24.447888 | F43: =LN(I27) -> 21.834536 | G43: =LN(G27) -> 25.461718 | H43: =LN(F27) -> 0.10634004 | I43: =LN(Ac!B23) -> 4.5584872 | J43: =LN(Ad!B24) -> 4.6022496
A44: 2016 | B44: =LN(B28) -> 26.23998 | C44: =LN(C28-H28) -> 24.377177 | D44: =LN(H28) -> 21.741998 | E44: =LN(D28-I28) -> 24.467749 | F44: =LN(I28) -> 22.055303 | G44: =LN(G28) -> 25.44902 | H44: =LN(F28) -> 0.06719125 | I44: =LN(Ac!B24) -> 4.5590528 | J44: =LN(Ad!B25) -> 4.5451753
A45: 2017 | B45: =LN(B29) -> 26.257787 | C45: =LN(C29-H29) -> 24.413142 | D45: =LN(H29) -> 21.640929 | E45: =LN(D29-I29) -> 24.537589 | F45: =LN(I29) -> 21.765003 | G45: =LN(G29) -> 25.471867 | H45: =LN(F29) -> 0.024887716 | I45: =LN(Ac!B25) -> 4.600864 | J45: =LN(Ad!B26) -> 4.4848129
A46: 2018 | B46: =LN(B30) -> 26.277233 | C46: =LN(C30-H30) -> 24.448318 | D46: =LN(H30) -> 21.969395 | E46: =LN(D30-I30) -> 24.531351 | F46: =LN(I30) -> 21.874252 | G46: =LN(G30) -> 25.47072 | H46: =LN(F30) -> 0.045164552 | I46: =LN(Ac!B26) -> 4.6355417 | J46: =LN(Ad!B27) -> 4.4597279
A47: 2019 | B47: =LN(B31) -> 26.28774 | C47: =LN(C31-H31) -> 24.455778 | D47: =LN(H31) -> 21.871275 | E47: =LN(D31-I31) -> 24.531236 | F47: =LN(I31) -> 21.954547 | G47: =LN(G31) -> 25.48765 | H47: =LN(F31) -> 0.039989648 | I47: =LN(Ac!B27) -> 4.6182429 | J47: =LN(Ad!B28) -> 4.4561651
A48: 2020 | B48: =LN(B32) -> 26.212884 | C48: =LN(C32-H32) -> 24.460347 | D48: =LN(H32) -> 22.117169 | E48: =LN(D32-I32) -> 24.715252 | F48: =LN(I32) -> 22.570362 | G48: =LN(G32) -> 25.410354 | H48: =LN(F32) -> 0.041333863 | I48: =LN(Ac!B28) -> 4.5846126 | J48: =LN(Ad!B29) -> 4.4057706
A49: 2021 | B49: =LN(B33) -> 26.301619 | C49: =LN(C33-H33) -> 24.424121 | D49: =LN(H33) -> 22.371316 | E49: =LN(D33-I33) -> 24.521897 | F49: =LN(I33) -> 21.894409 | G49: =LN(G33) -> 25.422884 | H49: =LN(F33) -> 0.10426992 | I49: =LN(Ac!B29) -> 4.6278619 | J49: =LN(Ad!B30) -> 4.4959193
D50: =AVERAGE(D38:D49) -> 21.954602 | F50: =AVERAGE(F38:F49) -> 21.966175
B51: CYCLES - OLS
A52: 2010 | B52: -0.0111111984993518 | C52: -0.07873152131211045 | D52: 0.2311436356944435 | E52: -0.02475019236083511 | F52: -0.02709287593538997 | G52: -0.1101169005596265 | H52: -0.008155291714805562
A53: 2011 | B53: 0.0007137970853513748 | C53: -0.02257131796914397 | D53: -0.0286651387361883 | E53: -0.02318992654837485 | F53: -0.1345726471279682 | G53: -0.02661193643798391 | H53: 0.0046888035148696 | I53: 0.02564476304782313 | J53: -0.06867680049163121
A54: 2012 | B54: -0.02292995992883064 | C54: 0.01678635297601824 | D54: 0.1112187152805771 | E54: 0.003015551152586393 | F54: -0.02769191422994677 | G54: -0.0003265219587386126 | H54: -0.004748065475242135 | I54: -0.01990449419667875 | J54: -0.01469249389820836
A55: 2013 | B55: 0.0565901635182862 | C55: 0.04311723489038421 | D55: -0.02950952850285535 | E55: 0.03148704850964539 | F55: 0.1610135757531725 | G55: 0.07373492686170394 | H55: -0.002861325113811167 | I55: 0.02306533721991984 | J55: 0.06610860933129358
A56: 2014 | B56: 0.05149165881840478 | C56: 0.05827642635624732 | D56: 0.1188891408814115 | E56: 0.02601304680150709 | F56: 0.2978860174209931 | G56: 0.08780121564134742 | H56: 0.006069921075587696 | I56: 0.002540752119328423 | J56: 0.0756495568872267
A57: 2015 | B57: 0.002009618318521821 | C57: 0.03176721973801183 | D57: -0.2199220515061205 | E57: -0.005249886248431701 | F57: -0.1186464076179856 | G57: 0.02310962031888786 | H57: 0.04661340964266607 | I57: -0.03404489512215331 | J57: 0.02707354042533952
A58: 2016 | B58: -0.02478316431876258 | C58: -0.01635601026592196 | D58: -0.2172598184703536 | E58: -0.01365399707767245 | F58: 0.07613651694263596 | G58: 0.004295438379332141 | H58: 0.007174878409533532 | I58: -0.03673089576738482 | J58: -0.00533295808452805
A59: 2017 | B59: -0.009295605337145042 | C59: 0.001853139976939255 | D59: -0.3276421171757893 | E59: 0.02791992443198929 | F59: -0.2401486817735427 | G59: 0.02102715280907603 | H59: -0.03541840062513991 | I59: 0.001828564281913282 | J59: -0.04102767473752536
A60: 2018 | B60: 0.007831525617171861 | C60: 0.01927437695970638 | D60: -0.008488064590421562 | E60: -0.006582674560351831 | F60: -0.1568845702866186 | G60: 0.01376400123321841 | H60: -0.01543130918067404 | I60: 0.03325464057274144 | J60: -0.04144483856587283
A61: 2019 | B61: 0.01601960509918876 | C61: 0.008978923987768728 | D61: -0.1159205410851549 | E61: -0.03496284903979036 | F61: -0.1025736656903001 | G61: 0.02457736006216074 | H61: -0.02089595792101828 | I61: 0.01270415567069007 | J61: -0.02033992641812018
A62: 2020 | B62: -0.06115570948959086 | C62: -0.004206932138166947 | D62: 0.1206603450834124 | E62: 0.1207870323031717 | F62: 0.4872562369946238 | G62: -0.05883420508949438 | H62: -0.01984148764632841 | I62: -0.02417778592010155 | J62: -0.0460667075061777
A63: 2021 | B63: 0.02525977933542647 | C63: -0.05818789319980289 | D63: 0.36549542312698 | E63: -0.1008330773634676 | F63: -0.2146815844497567 | G63: -0.05242015125995136 | H63: 0.04280482503436246 | I63: 0.01581985809390696 | J63: 0.06874969305820461
B64: SHOCKS - OLS (GL and GC are the residuals of an AR(1) process. The others are the cycle itself).
A65: 2012 | C65: 0.01316215155477036 | D65: -0.0286651387361883 | E65: -0.04254106387114265 | F65: -0.1345726471279682 | I65: 0.02564476304782313 | J65: -0.06867680049163121
A66: 2013 | C66: 0.02703068065219287 | D66: 0.1112187152805771 | E66: -0.01511567977281878 | F66: -0.02769191422994677 | I66: -0.01990449419667875 | J66: -0.01469249389820836
A67: 2014 | C67: 0.0354984994399624 | D67: -0.02950952850285535 | E67: 0.03384478147619276 | F67: 0.1610135757531725 | I67: 0.02306533721991984 | J67: 0.06610860933129358
A68: 2015 | C68: 0.0387070293316022 | D68: 0.1188891408814115 | E68: 0.05063144938665129 | F68: 0.2978860174209931 | I68: 0.002540752119328423 | J68: 0.0756495568872267
A69: 2016 | C69: 0.005317598665552196 | D69: -0.2199220515061205 | E69: 0.01508862399426464 | F69: -0.1186464076179856 | I69: -0.03404489512215331 | J69: 0.02707354042533952
A70: 2017 | C70: -0.03077403445051404 | D70: -0.2172598184703536 | E70: -0.01775866294213139 | F70: 0.07613651694263596 | I70: -0.03673089576738482 | J70: -0.00533295808452805
A71: 2018 | C71: 0.00927655800100138 | D71: -0.3276421171757893 | E71: 0.01724443679930268 | F71: -0.2401486817735427 | I71: 0.001828564281913282 | J71: -0.04102767473752536
A72: 2019 | C72: 0.01843330187585276 | D72: -0.008488064590421562 | E72: 0.01524674332246315 | F72: -0.1568845702866186 | I72: 0.03325464057274144 | J72: -0.04144483856587283
A73: 2020 | C73: 0.0002309619237337406 | D73: -0.1159205410851549 | E73: -0.04010956618490754 | F73: -0.1025736656903001 | I73: 0.01270415567069007 | J73: -0.02033992641812018
A74: 2021 | C74: -0.008282150060129346 | D74: 0.1206603450834124 | E74: 0.09345104706716222 | F74: 0.4872562369946238 | I74: -0.02417778592010155 | J74: -0.0460667075061777
C75: -0.05627851460730209 | D75: 0.36549542312698 | E75: -0.006394762911943034 | F75: -0.2146815844497567 | I75: 0.01581985809390696 | J75: 0.06874969305820461
K77: Proporções
F78: PIB | H78: GL | I78: IGL | J78: GL + IGL | K78: =I79/J79 -> 0.10812944
A79: 2009 | F79: 594054.64 | G79: DEE | H79: =0.113 -> 0.113 | I79: 0.0137 | J79: =H79+I79 -> 0.1267 | K79: =H79/J79 -> 0.89187056
A80: 2010 | B80: =SUBSTITUTE(C80,",",".") | F80: Juros | G80: Amortozição | H80: Shocks
A81: 2011 | B81: =SUBSTITUTE(C81,",",".") -> 4.60517018598809 | C81: 4.6051702 | E81: 2022 | F81: 552.90023 | G81: 368.84936 | H81: Juros | I81: Amort | J81: eps_bl | N81: (GL+IGL)*PIB*0,75 | O81: =J79*F79*0.75 -> 56450.042
A82: 2012 | B82: =SUBSTITUTE(C82,",",".") -> 4.63448674984461 | C82: 4.6344867 | E82: 2023 | F82: 1547.5626 | G82: 504.47744 | H82: =(F82/$F$79)/$H$79 -> 0.023053846 | I82: =(G82/$F$79)/$H$79 -> 0.0075151373 | J82: =H82+I82 -> 0.030568983 | O82: =F83+G83 -> 2970.7822
A83: 2013 | B83: =SUBSTITUTE(C83,",",".") -> 4.69062011033721 | C83: 4.6906201 | E83: 2024 | F83: 2229.9252 | G83: 740.85698 | H83: =(F83/$F$79)/$H$79 -> 0.033218916 | I83: =(G83/$F$79)/$H$79 -> 0.011036454 | J83: =H83+I83 -> 0.04425537 | M83: eps_tauc | O83: =F84+G84 -> 3926.0815
A84: 2014 | B84: =SUBSTITUTE(C84,",",".") -> 4.67549331515624 | C84: 4.6754933 | E84: 2025 | F84: 2873.5681 | G84: 1052.5134 | H84: =(F84/$F$79)/$H$79 -> 0.042807184 | I84: =(G84/$F$79)/$H$79 -> 0.01567916 | J84: =H84+I84 -> 0.058486345 | L84: 2024 | M84: =O82/$O$81/0.9 -> 0.058474166 | O84: =F85+G85 -> 4991.2499
A85: 2015 | B85: =SUBSTITUTE(C85,",",".") -> 4.60224955595745 | C85: 4.6022496 | E85: 2026 | F85: 3523.86 | G85: 1467.39 | H85: =(F85/$F$79)/$H$79 -> 0.052494501 | I85: =(G85/$F$79)/$H$79 -> 0.021859525 | J85: =H85+I85 -> 0.074354025 | L85: 2025 | M85: =O83/$O$81/0.9 -> 0.077277406 | O85: =F86+G86 -> 5947.0273
A86: 2016 | B86: =SUBSTITUTE(C86,",",".") -> 4.54517531471068 | C86: 4.5451753 | E86: 2027 | F86: 4178.675 | G86: 1768.3522 | H86: =(F86/$F$79)/$H$79 -> 0.062249199 | I86: =(G86/$F$79)/$H$79 -> 0.026342922 | J86: =H86+I86 -> 0.088592121 | L86: 2026 | M86: =O84/$O$81/0.9 -> 0.098243209 | O86: =F87+G87 -> 6478.2036
A87: 2017 | B87: =SUBSTITUTE(C87,",",".") -> 4.48481285532078 | C87: 4.4848129 | E87: 2028 | F87: 4302.3098 | G87: 2175.8937 | H87: =(F87/$F$79)/$H$79 -> 0.064090971 | I87: =(G87/$F$79)/$H$79 -> 0.032414017 | J87: =H87+I87 -> 0.096504987 | L87: 2027 | M87: =O85/$O$81/0.9 -> 0.11705586 | O87: =F88+G88 -> 7197.5914
A88: 2018 | B88: =SUBSTITUTE(C88,",",".") -> 4.45972794875553 | C88: 4.4597279 | E88: 2029 | F88: 4336.3591 | G88: 2861.2323 | H88: =(F88/$F$79)/$H$79 -> 0.064598198 | I88: =(G88/$F$79)/$H$79 -> 0.04262342 | J88: =H88+I88 -> 0.10722162 | L88: 2028 | M88: =O86/$O$81/0.9 -> 0.12751105 | O88: =F89+G89 -> 8039.3118
A89: 2019 | B89: =SUBSTITUTE(C89,",",".") -> 4.45616511816638 | C89: 4.4561651 | E89: 2030 | F89: 4339.1264 | G89: 3700.1854 | H89: =(F89/$F$79)/$H$79 -> 0.064639422 | I89: =(G89/$F$79)/$H$79 -> 0.055121199 | J89: =H89+I89 -> 0.11976062 | L89: 2029 | M89: =O87/$O$81/0.9 -> 0.14167082 | O89: =F90+G90 -> 8743.3962
A90: 2020 | B90: =SUBSTITUTE(C90,",",".") -> 4.40577059434142 | C90: 4.4057706 | E90: 2031 | F90: 4309.882 | G90: 4433.5142 | H90: =(F90/$F$79)/$H$79 -> 0.064203773 | I90: =(G90/$F$79)/$H$79 -> 0.066045506 | J90: =H90+I90 -> 0.13024928 | L90: 2030 | M90: =O88/$O$81/0.9 -> 0.15823848
A91: 2021 | B91: =SUBSTITUTE(C91,",",".") -> 4.4959192521689 | C91: 4.4959193 | L91: 2031 | M91: =O89/$O$81/0.9 -> 0.17209703
F92: Juros | G92: Amortozição | H92: Shocks
E93: 2022 | H93: Juros | I93: Amort | J93: eps_bl
E94: 2023 | H94: =(F94/$F$79)/$H$79 -> 0 | I94: =(G94/$F$79)/$H$79 -> 0 | J94: =H94+I94 -> 0
E95: 2024 | F95: =F83*1.1 -> 2452.9177 | G95: 740.85698 | H95: =(F95/$F$79)/$H$79 -> 0.036540808 | I95: =(G95/$F$79)/$H$79 -> 0.011036454 | J95: =H95+I95 -> 0.047577262
E96: 2025 | F96: =F84*1.1 -> 3160.9249 | G96: 1052.5134 | H96: =(F96/$F$79)/$H$79 -> 0.047087903 | I96: =(G96/$F$79)/$H$79 -> 0.01567916 | J96: =H96+I96 -> 0.062767063
E97: 2026 | F97: =F85*1.1 -> 3876.246 | G97: 1467.39 | H97: =(F97/$F$79)/$H$79 -> 0.057743951 | I97: =(G97/$F$79)/$H$79 -> 0.021859525 | J97: =H97+I97 -> 0.079603476
E98: 2027 | F98: =F86*1.1 -> 4596.5425 | G98: 1768.3522 | H98: =(F98/$F$79)/$H$79 -> 0.068474119 | I98: =(G98/$F$79)/$H$79 -> 0.026342922 | J98: =H98+I98 -> 0.094817041
E99: 2028 | F99: =F87*1.1 -> 4732.5408 | G99: 2175.8937 | H99: =(F99/$F$79)/$H$79 -> 0.070500068 | I99: =(G99/$F$79)/$H$79 -> 0.032414017 | J99: =H99+I99 -> 0.10291408
E100: 2029 | F100: =F88*1.1 -> 4769.995 | G100: 2861.2323 | H100: =(F100/$F$79)/$H$79 -> 0.071058018 | I100: =(G100/$F$79)/$H$79 -> 0.04262342 | J100: =H100+I100 -> 0.11368144
E101: 2030 | F101: =F89*1.1 -> 4773.039 | G101: 3700.1854 | H101: =(F101/$F$79)/$H$79 -> 0.071103365 | I101: =(G101/$F$79)/$H$79 -> 0.055121199 | J101: =H101+I101 -> 0.12622456
E102: 2031 | F102: =F90*1.1 -> 4740.8702 | G102: 4433.5142 | H102: =(F102/$F$79)/$H$79 -> 0.07062415 | I102: =(G102/$F$79)/$H$79 -> 0.066045506 | J102: =H102+I102 -> 0.13666966
F105: PIB | H105: IGL
...

Sheet Correlations
B1: CYCLE_AC | C1: CYCLE_AD | D1: CYCLE_GC | E1: CYCLE_GL | F1: CYCLE_IGC | G1: CYCLE_IGL | H1: CYCLE_INFLATION | I1: CYCLE_W | J1: CYCLE_Y
A2: 2010 | D2: -0.02475019236083511 | E2: -0.07873152131211045 | F2: -0.02709287593538997 | G2: 0.2311436356944435 | H2: -0.008155291714805562 | I2: -0.1101169005596265 | J2: -0.0111111984993518
A3: 2011 | B3: 0.02564476304782313 | C3: -0.06867680049163121 | D3: -0.02318992654837485 | E3: -0.02257131796914397 | F3: -0.1345726471279682 | G3: -0.0286651387361883 | H3: 0.0046888035148696 | I3: -0.02661193643798391 | J3: 0.0007137970853513748
A4: 2012 | B4: -0.01990449419667875 | C4: -0.01469249389820836 | D4: 0.003015551152586393 | E4: 0.01678635297601824 | F4: -0.02769191422994677 | G4: 0.1112187152805771 | H4: -0.004748065475242135 | I4: -0.0003265219587386126 | J4: -0.02292995992883064
A5: 2013 | B5: 0.02306533721991984 | C5: 0.06610860933129358 | D5: 0.03148704850964539 | E5: 0.04311723489038421 | F5: 0.1610135757531725 | G5: -0.02950952850285535 | H5: -0.002861325113811167 | I5: 0.07373492686170394 | J5: 0.0565901635182862
A6: 2014 | B6: 0.002540752119328423 | C6: 0.0756495568872267 | D6: 0.02601304680150709 | E6: 0.05827642635624732 | F6: 0.2978860174209931 | G6: 0.1188891408814115 | H6: 0.006069921075587696 | I6: 0.08780121564134742 | J6: 0.05149165881840478
A7: 2015 | B7: -0.03404489512215331 | C7: 0.02707354042533952 | D7: -0.005249886248431701 | E7: 0.03176721973801183 | F7: -0.1186464076179856 | G7: -0.2199220515061205 | H7: 0.04661340964266607 | I7: 0.02310962031888786 | J7: 0.002009618318521821
A8: 2016 | B8: -0.03673089576738482 | C8: -0.00533295808452805 | D8: -0.01365399707767245 | E8: -0.01635601026592196 | F8: 0.07613651694263596 | G8: -0.2172598184703536 | H8: 0.007174878409533532 | I8: 0.004295438379332141 | J8: -0.02478316431876258
A9: 2017 | B9: 0.001828564281913282 | C9: -0.04102767473752536 | D9: 0.02791992443198929 | E9: 0.001853139976939255 | F9: -0.2401486817735427 | G9: -0.3276421171757893 | H9: -0.03541840062513991 | I9: 0.02102715280907603 | J9: -0.009295605337145042
A10: 2018 | B10: 0.03325464057274144 | C10: -0.04144483856587283 | D10: -0.006582674560351831 | E10: 0.01927437695970638 | F10: -0.1568845702866186 | G10: -0.008488064590421562 | H10: -0.01543130918067404 | I10: 0.01376400123321841 | J10: 0.007831525617171861
A11: 2019 | B11: 0.01270415567069007 | C11: -0.02033992641812018 | D11: -0.03496284903979036 | E11: 0.008978923987768728 | F11: -0.1025736656903001 | G11: -0.1159205410851549 | H11: -0.02089595792101828 | I11: 0.02457736006216074 | J11: 0.01601960509918876
A12: 2020 | B12: -0.02417778592010155 | C12: -0.0460667075061777 | D12: 0.1207870323031717 | E12: -0.004206932138166947 | F12: 0.4872562369946238 | G12: 0.1206603450834124 | H12: -0.01984148764632841 | I12: -0.05883420508949438 | J12: -0.06115570948959086
A13: 2021 | B13: 0.01581985809390696 | C13: 0.06874969305820461 | D13: -0.1008330773634676 | E13: -0.05818789319980289 | F13: -0.2146815844497567 | G13: 0.36549542312698 | H13: 0.04280482503436246 | I13: -0.05242015125995136 | J13: 0.02525977933542647

Sheet Taylor-RS
A1: Period | B1: Anualized Interest rate (Selic) | C1: 100 | G1: Output Gap - Monthly Commerce Data | I1: Wide Commerce RS data - Nominal revenues index and sells | K1: Accumulated 12 months | L1: Potencial | M1: Gap | P1: Inflation POA | R1: 100 | AA1: Volume de vendas no comÃ©rcio varejista ampliado
A2: 38718 | B2: 0.17685484 | C2: =C1*(1+B2/12) -> 101.47379 | G2: -0.005576325 | I2: 37987 | J2: 21.98665 | O2: 38353 | P2: 0.86 | R2: =R1*(1+P2/100) -> 100.86 | AB2: Rio Grande do Sul
A3: 38749 | B3: 0.1725 | C3: =C2*(1+B3/12) -> 102.93248 | G3: -0.011560346 | I3: 38018 | J3: 20.82702 | O3: 38384 | P3: 0.54 | R3: =R2*(1+P3/100) -> 101.40464 | AA3: 37987 | AB3: 52.37623
A4: 38777 | B4: 0.16693548 | C4: =C3*(1+B4/12) -> 104.3644 | G4: -0.01508146 | I4: 38047 | J4: 25.04808 | O4: 38412 | P4: 0.48 | R4: =R3*(1+P4/100) -> 101.89139 | AA4: 38018 | AB4: 49.51461
A5: 38808 | B5: 0.162 | C5: =C4*(1+B5/12) -> 105.77332 | G5: -0.019074644 | I5: 38078 | J5: 24.49146 | O5: 38443 | P5: 1.87 | R5: =R4*(1+P5/100) -> 103.79676 | AA5: marÃ§o 2004 | AB5: 59.05333
A6: 38838 | B6: 0.1575 | C6: =C5*(1+B6/12) -> 107.16159 | G6: -0.01836251 | I6: 38108 | J6: 25.83664 | O6: 38473 | P6: 0.35 | R6: =R5*(1+P6/100) -> 104.16004 | T6: =CORREL(R25:R229,T25:T229) -> 0.96536981 | AA6: 38078 | AB6: 57.49245
A7: 38869 | B7: 0.1525 | C7: =C6*(1+B7/12) -> 108.52344 | G7: -0.024786701 | I7: 38139 | J7: 25.18724 | O7: 38504 | P7: 0.15 | R7: =R6*(1+P7/100) -> 104.31628 | AA7: 38108 | AB7: 60.18063
A8: 38899 | B8: 0.15056452 | C8: =C7*(1+B8/12) -> 109.88509 | G8: -0.027981235 | I8: 38169 | J8: 26.43965 | O8: 38534 | P8: 0.21 | R8: =R7*(1+P8/100) -> 104.53535 | AA8: 38139 | AB8: 57.66588
A9: 38930 | B9: 0.14733871 | C9: =C8*(1+B9/12) -> 111.23428 | G9: -0.029563448 | I9: 38200 | J9: 26.20772 | O9: 38565 | P9: 0.27 | R9: =R8*(1+P9/100) -> 104.81759 | T9: =CORREL(P14:P229,V14:V229) -> 0.84930365 | AA9: 38169 | AB9: 60.18063
A10: 38961 | B10: 0.1425 | C10: =C9*(1+B10/12) -> 112.55519 | G10: -0.028290341 | I10: 38231 | J10: 25.09447 | O10: 38596 | P10: -0.11 | R10: =R9*(1+P10/100) -> 104.70229 | AA10: 38200 | AB10: 59.31347
A11: 38991 | B11: 0.14040323 | C11: =C10*(1+B11/12) -> 113.87211 | G11: -0.027737154 | I11: 38261 | J11: 27.41374 | O11: 38626 | P11: 0.55 | R11: =R10*(1+P11/100) -> 105.27816 | AA11: 38231 | AB11: 56.36514
A12: 39022 | B12: 0.13733333 | C12: =C11*(1+B12/12) -> 115.17532 | G12: -0.030005414 | I12: 38292 | J12: 27.2282 | O12: 38657 | P12: 0.44 | R12: =R11*(1+P12/100) -> 105.74138 | AA12: 38261 | AB12: 61.1345
A13: 39052 | B13: 0.1325 | C13: =C12*(1+B13/12) -> 116.44704 | D13: =C13/C1-1 -> 0.16447045 | G13: -0.032405565 | I13: 38322 | J13: 36.69081 | K13: =SUM(J2:J13) -> 312.45168 | L13: 307.46223 | M13: =(K13-L13)/L13 -> 0.01622784 | O13: 38687 | P13: 0.12 | Q13: 100 | R13: =R12*(1+P13/100) -> 105.86827 | U13: 100 | X13: Brazil | Y13: Poa | AA13: 38292 | AB13: 60.35406
A14: 39083 | B14: 0.13193548 | C14: =C13*(1+B14/12) -> 117.72734 | G14: -0.032164251 | I14: 38353 | J14: 25.51194 | K14: =SUM(J3:J14) -> 315.97697 | L14: 308.17507 | M14: =(K14-L14)/L14 -> 0.025316444 | O14: 38718 | P14: 0.4 | Q14: =Q13*(1+P14/100) -> 100.4 | U14: =U13*W14 -> 100.59 | V14: 0.59 | W14: =1+V14/100 -> 1.0059 | X14: =SUBSTITUTE(V14,",",".") -> 0.59 | Y14: =SUBSTITUTE(P14,",",".") -> 0.4 | AA14: 38322 | AB14: 80.5588 | AC14: 714.18973
A15: 39114 | B15: 0.13 | C15: =C14*(1+B15/12) -> 119.00272 | G15: -0.033325927 | I15: 38384 | J15: 23.05352 | K15: =SUM(J4:J15) -> 318.20347 | L15: 308.88826 | M15: =(K15-L15)/L15 -> 0.030157214 | O15: 38749 | P15: 0.18 | Q15: =Q14*(1+P15/100) -> 100.58072 | U15: =U14*W15 -> 101.00242 | V15: 0.41 | W15: =1+V15/100 -> 1.0041 | X15: =SUBSTITUTE(V15,",",".") -> 0.41 | Y15: =SUBSTITUTE(P15,",",".") -> 0.18 | AA15: 38353 | AB15: 55.5847 | AC15: 717.3982
A16: 39142 | B16: 0.12806452 | C16: =C15*(1+B16/12) -> 120.27272 | G16: -0.033535943 | I16: 38412 | J16: 26.99627 | K16: =SUM(J5:J16) -> 320.15166 | L16: 309.60268 | M16: =(K16-L16)/L16 -> 0.034072629 | O16: 38777 | P16: 0.52 | Q16: =Q15*(1+P16/100) -> 101.10374 | U16: =U15*W16 -> 101.43673 | V16: 0.43 | W16: =1+V16/100 -> 1.0043 | X16: =SUBSTITUTE(V16,",",".") -> 0.43 | Y16: =SUBSTITUTE(P16,",",".") -> 0.52 | AA16: 38384 | AB16: 50.12162 | AC16: 718.00521
A17: 39173 | B17: 0.1265 | C17: =C16*(1+B17/12) -> 121.54059 | G17: -0.032673612 | I17: 38443 | J17: 25.97579 | K17: =SUM(J6:J17) -> 321.63599 | L17: 310.31987 | M17: =(K17-L17)/L17 -> 0.03646597 | O17: 38808 | P17: 0.48 | Q17: =Q16*(1+P17/100) -> 101.58904 | U17: =U16*W17 -> 101.64975 | V17: 0.21 | W17: =1+V17/100 -> 1.0021 | X17: =SUBSTITUTE(V17,",",".") -> 0.21 | Y17: =SUBSTITUTE(P17,",",".") -> 0.48 | AA17: marÃ§o 2005 | AB17: 58.61975 | AC17: 717.57163
A18: 39203 | B18: 0.125 | C18: =C17*(1+B18/12) -> 122.80664 | G18: -0.030756093 | I18: 38473 | J18: 26.2541 | K18: =SUM(J7:J18) -> 322.05345 | L18: 311.0421 | M18: =(K18-L18)/L18 -> 0.035401465 | O18: 38838 | P18: 0.25 | Q18: =Q17*(1+P18/100) -> 101.84301 | U18: =U17*W18 -> 101.7514 | V18: 0.1 | W18: =1+V18/100 -> 1.001 | X18: =SUBSTITUTE(V18,",",".") -> 0.1 | Y18: =SUBSTITUTE(P18,",",".") -> 0.25 | AA18: 38443 | AB18: 55.49799 | AC18: 715.57717
A19: 39234 | B19: 0.12116667 | C19: =C18*(1+B19/12) -> 124.04665 | G19: -0.02699475 | I19: 38504 | J19: 25.79025 | K19: =SUM(J8:J19) -> 322.65646 | L19: 311.77242 | M19: =(K19-L19)/L19 -> 0.034910194 | O19: 38869 | P19: -0.13 | Q19: =Q18*(1+P19/100) -> 101.71061 | U19: =U18*W19 -> 101.53772 | V19: -0.21 | W19: =1+V19/100 -> 0.9979 | X19: =SUBSTITUTE(V19,",",".") -> -0.21 | Y19: =SUBSTITUTE(P19,",",".") -> -0.13 | AA19: 38473 | AB19: 55.93157 | AC19: 711.32811
A20: 39264 | B20: 0.11790323 | C20: =C19*(1+B20/12) -> 125.26544 | G20: -0.025285379 | I20: 38534 | J20: 25.88302 | K20: =SUM(J9:J20) -> 322.09983 | L20: 312.51465 | M20: =(K20-L20)/L20 -> 0.030671128 | O20: 38899 | P20: 0.14 | Q20: =Q19*(1+P20/100) -> 101.85301 | U20: =U19*W20 -> 101.73064 | V20: 0.19 | W20: =1+V20/100 -> 1.0019 | X20: =SUBSTITUTE(V20,",",".") -> 0.19 | Y20: =SUBSTITUTE(P20,",",".") -> 0.14 | AA20: 38504 | AB20: 55.06441 | AC20: 708.72664
A21: 39295 | B21: 0.115 | C21: =C20*(1+B21/12) -> 126.4659 | G21: -0.019493373 | I21: 38565 | J21: 25.97579 | K21: =SUM(J10:J21) -> 321.8679 | L21: 313.27337 | M21: =(K21-L21)/L21 -> 0.027434617 | O21: 38930 | P21: 0.02 | Q21: =Q20*(1+P21/100) -> 101.87338 | U21: =U20*W21 -> 101.78151 | V21: 0.05 | W21: =1+V21/100 -> 1.0005 | X21: =SUBSTITUTE(V21,",",".") -> 0.05 | Y21: =SUBSTITUTE(P21,",",".") -> 0.02 | AA21: 38534 | AB21: 55.41127 | AC21: 703.95728
A22: 39326 | B22: 0.11291667 | C22: =C21*(1+B22/12) -> 127.65591 | G22: -0.018097609 | I22: 38596 | J22: 24.07399 | K22: =SUM(J11:J22) -> 320.84742 | L22: 314.0538 | M22: =(K22-L22)/L22 -> 0.021632026 | O22: 38961 | P22: 0.11 | Q22: =Q21*(1+P22/100) -> 101.98544 | U22: =U21*W22 -> 101.99525 | V22: 0.21 | W22: =1+V22/100 -> 1.0021 | X22: =SUBSTITUTE(V22,",",".") -> 0.21 | Y22: =SUBSTITUTE(P22,",",".") -> 0.11 | AA22: 38565 | AB22: 55.5847 | AC22: 700.22851
A23: 39356 | B23: 0.1125 | C23: =C22*(1+B23/12) -> 128.85268 | G23: -0.010312753 | I23: 38626 | J23: 25.65109 | K23: =SUM(J12:J23) -> 319.08477 | L23: 314.86179 | M23: =(K23-L23)/L23 -> 0.013412156 | O23: 38991 | P23: 0.31 | Q23: =Q22*(1+P23/100) -> 102.3016 | U23: =U22*W23 -> 102.33183 | V23: 0.33 | W23: =1+V23/100 -> 1.0033 | X23: =SUBSTITUTE(V23,",",".") -> 0.33 | Y23: =SUBSTITUTE(P23,",",".") -> 0.31 | AA23: 38596 | AB23: 51.6825 | AC23: 695.54587
A24: 39387 | B24: 0.1125 | C24: =C23*(1+B24/12) -> 130.06068 | G24: -0.0037670152 | I24: 38657 | J24: 26.67157 | K24: =SUM(J13:J24) -> 318.52814 | L24: 315.70366 | M24: =(K24-L24)/L24 -> 0.0089466273 | O24: 39022 | P24: 0.13 | Q24: =Q23*(1+P24/100) -> 102.43459 | U24: =U23*W24 -> 102.64906 | V24: 0.31 | W24: =1+V24/100 -> 1.0031 | X24: =SUBSTITUTE(V24,",",".") -> 0.31 | Y24: =SUBSTITUTE(P24,",",".") -> 0.13 | AA24: 38626 | AB24: 54.71755 | AC24: 689.12892
A25: 39417 | B25: 0.1125 | C25: =C24*(1+B25/12) -> 131.27999 | D25: =C25/C13-1 -> 0.12737936 | G25: 4.3512721e-05 | I25: 38687 | J25: 34.97455 | K25: =SUM(J14:J25) -> 316.81188 | L25: 316.58599 | M25: =(K25-L25)/L25 -> 0.00071351972 | O25: 39052 | P25: 0.23 | Q25: =Q24*(1+P25/100) -> 102.67019 | R25: =Q25/Q13-1 -> 0.02670187 | S25: 0.045 | T25: =U25/U13-1 -> 0.03141775 | U25: =U24*W25 -> 103.14177 | V25: 0.48 | W25: =1+V25/100 -> 1.0048 | X25: =SUBSTITUTE(V25,",",".") -> 0.48 | Y25: =SUBSTITUTE(P25,",",".") -> 0.23 | AA25: 38657 | AB25: 56.71201 | AC25: 685.48687
A26: 39448 | B26: 0.1125 | C26: =C25*(1+B26/12) -> 132.51074 | G26: 0.0028493203 | I26: 38718 | J26: 24.44508 | K26: =SUM(J15:J26) -> 315.74502 | L26: 317.51559 | M26: =(K26-L26)/L26 -> -0.005576325 | O26: 39083 | P26: -0.07 | Q26: =Q25*(1+P26/100) -> 102.59832 | R26: =Q26/Q14-1 -> 0.021895597 | S26: 0.045 | T26: =U26/U14-1 -> 0.029879698 | U26: =U25*W26 -> 103.5956 | V26: 0.44 | W26: =1+V26/100 -> 1.0044 | X26: =SUBSTITUTE(V26,",",".") -> 0.44 | Y26: =SUBSTITUTE(P26,",",".") -> -0.07 | AA26: 38687 | AB26: 74.66214 | AC26: 679.59021
A27: 39479 | B27: 0.1125 | C27: =C26*(1+B27/12) -> 133.75303 | G27: 0.0090971865 | I27: 38749 | J27: 22.12581 | K27: =SUM(J16:J27) -> 314.81731 | L27: 318.49927 | M27: =(K27-L27)/L27 -> -0.011560346 | O27: 39114 | P27: -0.04 | Q27: =Q26*(1+P27/100) -> 102.55728 | R27: =Q27/Q15-1 -> 0.019651466 | S27: 0.045 | T27: =U27/U15-1 -> 0.0301874 | U27: =U26*W27 -> 104.05142 | V27: 0.44 | W27: =1+V27/100 -> 1.0044 | X27: =SUBSTITUTE(V27,",",".") -> 0.44 | Y27: =SUBSTITUTE(P27,",",".") -> -0.04 | AA27: 38718 | AB27: 51.85593 | AC27: 675.86144
A28: 39508 | B28: 0.1125 | C28: =C27*(1+B28/12) -> 135.00697 | G28: 0.012094901 | I28: 38777 | J28: 26.9035 | K28: =SUM(J17:J28) -> 314.72454 | L28: 319.54373 | M28: =(K28-L28)/L28 -> -0.01508146 | O28: 39142 | P28: 0.55 | Q28: =Q27*(1+P28/100) -> 103.12134 | R28: =Q28/Q16-1 -> 0.019955779 | S28: 0.045 | T28: =U28/U16-1 -> 0.029571934 | U28: =U27*W28 -> 104.43641 | V28: 0.37 | W28: =1+V28/100 -> 1.0037 | X28: =SUBSTITUTE(V28,",",".") -> 0.37 | Y28: =SUBSTITUTE(P28,",",".") -> 0.55 | AA28: 38749 | AB28: 46.91314 | AC28: 672.65296
A29: 39539 | B29: 0.11483333 | C29: =C28*(1+B29/12) -> 136.29891 | G29: 0.018376112 | I29: 38808 | J29: 25.79025 | K29: =SUM(J18:J29) -> 314.539 | L29: 320.65539 | M29: =(K29-L29)/L29 -> -0.019074644 | O29: 39173 | P29: 0.42 | Q29: =Q28*(1+P29/100) -> 103.55445 | R29: =Q29/Q17-1 -> 0.019346729 | S29: 0.045 | T29: =U29/U17-1 -> 0.0299829 | U29: =U28*W29 -> 104.6975 | V29: 0.25 | W29: =1+V29/100 -> 1.0025 | X29: =SUBSTITUTE(V29,",",".") -> 0.25 | Y29: =SUBSTITUTE(P29,",",".") -> 0.42 | AA29: marÃ§o 2006 | AB29: 56.88544 | AC29: 670.91865
A30: 39569 | B30: 0.1175 | C30: =C29*(1+B30/12) -> 137.6335 | G30: 0.02197609 | I30: 38838 | J30: 27.64566 | K30: =SUM(J19:J30) -> 315.93056 | L30: 321.84036 | M30: =(K30-L30)/L30 -> -0.01836251 | O30: 39203 | P30: 0.49 | Q30: =Q29*(1+P30/100) -> 104.06187 | R30: =Q30/Q18-1 -> 0.02178706 | S30: 0.045 | T30: =U30/U18-1 -> 0.031835017 | U30: =U29*W30 -> 104.99065 | V30: 0.28 | W30: =1+V30/100 -> 1.0028 | X30: =SUBSTITUTE(V30,",",".") -> 0.28 | Y30: =SUBSTITUTE(P30,",",".") -> 0.49 | AA30: 38808 | AB30: 54.63083 | AC30: 670.05149
A31: 39600 | B31: 0.12183333 | C31: =C30*(1+B31/12) -> 139.03086 | G31: 0.028451377 | I31: 38869 | J31: 24.95531 | K31: =SUM(J20:J31) -> 315.09562 | L31: 323.10431 | M31: =(K31-L31)/L31 -> -0.024786701 | O31: 39234 | P31: 0.23 | Q31: =Q30*(1+P31/100) -> 104.30121 | R31: =Q31/Q19-1 -> 0.025470282 | S31: 0.045 | T31: =U31/U19-1 -> 0.036901648 | U31: =U30*W31 -> 105.28463 | V31: 0.28 | W31: =1+V31/100 -> 1.0028 | X31: =SUBSTITUTE(V31,",",".") -> 0.28 | Y31: =SUBSTITUTE(P31,",",".") -> 0.23 | AA31: 38838 | AB31: 58.27289 | AC31: 672.39281
A32: 39630 | B32: 0.12443548 | C32: =C31*(1+B32/12) -> 140.47256 | G32: 0.035927383 | I32: 38899 | J32: 26.16133 | K32: =SUM(J21:J32) -> 315.37393 | L32: 324.45251 | M32: =(K32-L32)/L32 -> -0.027981235 | O32: 39264 | P32: 0.54 | Q32: =Q31*(1+P32/100) -> 104.86444 | R32: =Q32/Q20-1 -> 0.029566428 | S32: 0.045 | T32: =U32/U20-1 -> 0.037419116 | U32: =U31*W32 -> 105.53731 | V32: 0.24 | W32: =1+V32/100 -> 1.0024 | X32: =SUBSTITUTE(V32,",",".") -> 0.24 | Y32: =SUBSTITUTE(P32,",",".") -> 0.54 | AA32: 38869 | AB32: 52.89652 | AC32: 670.22492
A33: 39661 | B33: 0.13 | C33: =C32*(1+B33/12) -> 141.99435 | G33: 0.036249318 | I33: 38930 | J33: 26.85711 | K33: =SUM(J22:J33) -> 316.25525 | L33: 325.88967 | M33: =(K33-L33)/L33 -> -0.029563448 | O33: 39295 | P33: 0.33 | Q33: =Q32*(1+P33/100) -> 105.21049 | R33: =Q33/Q21-1 -> 0.032757446 | S33: 0.045 | T33: =U33/U21-1 -> 0.041774099 | U33: =U32*W33 -> 106.03334 | V33: 0.47 | W33: =1+V33/100 -> 1.0047 | X33: =SUBSTITUTE(V33,",",".") -> 0.47 | Y33: =SUBSTITUTE(P33,",",".") -> 0.33 | AA33: 38899 | AB33: 55.41127 | AC33: 670.22492
A34: 39692 | B34: 0.135 | C34: =C33*(1+B34/12) -> 143.59179 | G34: 0.041941994 | I34: 38961 | J34: 25.97579 | K34: =SUM(J23:J34) -> 318.15705 | L34: 327.41987 | M34: =(K34-L34)/L34 -> -0.028290341 | O34: 39326 | P34: -0.12 | Q34: =Q33*(1+P34/100) -> 105.08424 | R34: =Q34/Q22-1 -> 0.030384714 | S34: 0.045 | T34: =U34/U22-1 -> 0.041462221 | U34: =U33*W34 -> 106.2242 | V34: 0.18 | W34: =1+V34/100 -> 1.0018 | X34: =SUBSTITUTE(V34,",",".") -> 0.18 | Y34: =SUBSTITUTE(P34,",",".") -> -0.12 | AA34: 38930 | AB34: 56.88544 | AC34: 671.52566
A35: 39722 | B35: 0.1375 | C35: =C34*(1+B35/12) -> 145.23711 | G35: 0.040992829 | I35: 38991 | J35: 27.41374 | K35: =SUM(J24:J35) -> 319.9197 | L35: 329.04651 | M35: =(K35-L35)/L35 -> -0.027737154 | O35: 39356 | P35: 0.24 | Q35: =Q34*(1+P35/100) -> 105.33644 | R35: =Q35/Q23-1 -> 0.029665674 | S35: 0.045 | T35: =U35/U23-1 -> 0.04115081 | U35: =U34*W35 -> 106.54287 | V35: 0.3 | W35: =1+V35/100 -> 1.003 | X35: =SUBSTITUTE(V35,",",".") -> 0.3 | Y35: =SUBSTITUTE(P35,",",".") -> 0.24 | AA35: 38961 | AB35: 55.23784 | AC35: 675.081
A36: 39753 | B36: 0.1375 | C36: =C35*(1+B36/12) -> 146.90128 | G36: 0.034854515 | I36: 39022 | J36: 27.59928 | K36: =SUM(J25:J36) -> 320.84741 | L36: 330.77237 | M36: =(K36-L36)/L36 -> -0.030005414 | O36: 39387 | P36: 0.58 | Q36: =Q35*(1+P36/100) -> 105.94739 | R36: =Q36/Q24-1 -> 0.034293153 | S36: 0.045 | T36: =U36/U24-1 -> 0.041877364 | U36: =U35*W36 -> 106.94773 | V36: 0.38 | W36: =1+V36/100 -> 1.0038 | X36: =SUBSTITUTE(V36,",",".") -> 0.38 | Y36: =SUBSTITUTE(P36,",",".") -> 0.58 | AA36: 38991 | AB36: 57.92602 | AC36: 678.28947
A37: 39783 | B37: 0.1375 | C37: =C36*(1+B37/12) -> 148.58453 | D37: =C37/C25-1 -> 0.13181393 | G37: 0.030940531 | I37: 39052 | J37: 35.94864 | K37: =SUM(J26:J37) -> 321.8215 | L37: 332.59958 | M37: =(K37-L37)/L37 -> -0.032405565 | O37: 39417 | P37: 0.51 | Q37: =Q36*(1+P37/100) -> 106.48772 | R37: =Q37/Q25-1 -> 0.037182529 | S37: 0.045 | T37: =U37/U25-1 -> 0.044573304 | U37: =U36*W37 -> 107.73914 | V37: 0.74 | W37: =1+V37/100 -> 1.0074 | X37: =SUBSTITUTE(V37,",",".") -> 0.74 | Y37: =SUBSTITUTE(P37,",",".") -> 0.51 | AA37: 39022 | AB37: 58.3596 | AC37: 679.93706
A38: 39814 | B38: 0.13427419 | C38: =C37*(1+B38/12) -> 150.24712 | G38: 0.025866754 | I38: 39083 | J38: 26.39326 | K38: =SUM(J27:J38) -> 323.76968 | L38: 334.52957 | M38: =(K38-L38)/L38 -> -0.032164251 | O38: 39448 | P38: 0.12 | Q38: =Q37*(1+P38/100) -> 106.61551 | R38: =Q38/Q26-1 -> 0.039154556 | S38: 0.045 | T38: =U38/U26-1 -> 0.045613302 | U38: =U37*W38 -> 108.32094 | V38: 0.54 | W38: =1+V38/100 -> 1.0054 | X38: =SUBSTITUTE(V38,",",".") -> 0.54 | Y38: =SUBSTITUTE(P38,",",".") -> 0.12 | AA38: 39052 | AB38: 76.39645 | AC38: 681.67137 | AD38: 682.16793 | AE38: -0.00072791098
A39: 39845 | B39: 0.1275 | C39: =C38*(1+B39/12) -> 151.84349 | G39: 0.018180055 | I39: 39114 | J39: 23.70291 | K39: =SUM(J28:J39) -> 325.34678 | L39: 336.56306 | M39: =(K39-L39)/L39 -> -0.033325927 | O39: 39479 | P39: 0.36 | Q39: =Q38*(1+P39/100) -> 106.99933 | R39: =Q39/Q27-1 -> 0.043312837 | S39: 0.045 | T39: =U39/U27-1 -> 0.046133818 | U39: =U38*W39 -> 108.85171 | V39: 0.49 | W39: =1+V39/100 -> 1.0049 | X39: =SUBSTITUTE(V39,",",".") -> 0.49 | Y39: =SUBSTITUTE(P39,",",".") -> 0.36 | AA39: 39083 | AB39: 55.84485 | AC39: 685.66029 | AD39: 687.97399 | AE39: -0.0033630593
A40: 39873 | B40: 0.11782258 | C40: =C39*(1+B40/12) -> 153.33437 | G40: 0.015374296 | I40: 39142 | J40: 28.89807 | K40: =SUM(J29:J40) -> 327.34135 | L40: 338.69997 | M40: =(K40-L40)/L40 -> -0.033535943 | O40: 39508 | P40: 0.73 | Q40: =Q39*(1+P40/100) -> 107.78042 | R40: =Q40/Q28-1 -> 0.045180528 | S40: 0.045 | T40: =U40/U28-1 -> 0.047280323 | U40: =U39*W40 -> 109.3742 | V40: 0.48 | W40: =1+V40/100 -> 1.0048 | X40: =SUBSTITUTE(V40,",",".") -> 0.48 | Y40: =SUBSTITUTE(P40,",",".") -> 0.73 | AA40: 39114 | AB40: 50.38177 | AC40: 689.12892 | AD40: 693.78001 | AE40: -0.0067039877
A41: 39904 | B41: 0.11216667 | C41: =C40*(1+B41/12) -> 154.76762 | G41: 0.0068194406 | I41: 39173 | J41: 28.24867 | K41: =SUM(J30:J41) -> 329.79977 | L41: 340.93949 | M41: =(K41-L41)/L41 -> -0.032673612 | O41: 39539 | P41: 0.91 | Q41: =Q40*(1+P41/100) -> 108.76122 | R41: =Q41/Q29-1 -> 0.050280493 | S41: 0.045 | T41: =U41/U29-1 -> 0.050414329 | U41: =U40*W41 -> 109.97575 | V41: 0.55 | W41: =1+V41/100 -> 1.0055 | X41: =SUBSTITUTE(V41,",",".") -> 0.55 | Y41: =SUBSTITUTE(P41,",",".") -> 0.91 | AA41: marÃ§o 2007 | AB41: 60.96107 | AC41: 693.20455 | AD41: 699.58581 | AE41: -0.0091214805
A42: 39934 | B42: 0.1025 | C42: =C41*(1+B42/12) -> 156.0896 | G42: -0.00037137894 | I42: 39203 | J42: 30.56794 | K42: =SUM(J31:J42) -> 332.72205 | L42: 343.28 | M42: =(K42-L42)/L42 -> -0.030756093 | O42: 39569 | P42: 0.89 | Q42: =Q41*(1+P42/100) -> 109.7292 | R42: =Q42/Q30-1 -> 0.05446113 | S42: 0.045 | T42: =U42/U30-1 -> 0.055756484 | U42: =U41*W42 -> 110.84456 | V42: 0.79 | W42: =1+V42/100 -> 1.0079 | X42: =SUBSTITUTE(V42,",",".") -> 0.79 | Y42: =SUBSTITUTE(P42,",",".") -> 0.89 | AA42: 39173 | AB42: 59.22676 | AC42: 697.80048 | AD42: 705.39086 | AE42: -0.010760525
A43: 39965 | B43: 0.096166667 | C43: =C42*(1+B43/12) -> 157.34048 | G43: -0.0044864115 | I43: 39234 | J43: 28.61976 | K43: =SUM(J32:J43) -> 336.3865 | L43: 345.7191 | M43: =(K43-L43)/L43 -> -0.02699475 | O43: 39600 | P43: 0.9 | Q43: =Q42*(1+P43/100) -> 110.71676 | R43: =Q43/Q31-1 -> 0.061509807 | S43: 0.045 | T43: =U43/U31-1 -> 0.060599404 | U43: =U42*W43 -> 111.66481 | V43: 0.74 | W43: =1+V43/100 -> 1.0074 | X43: =SUBSTITUTE(V43,",",".") -> 0.74 | Y43: =SUBSTITUTE(P43,",",".") -> 0.9 | AA43: 39203 | AB43: 63.9094 | AC43: 703.43699 | AD43: 711.1942 | AE43: -0.010907295
A44: 39995 | B44: 0.091048387 | C44: =C43*(1+B44/12) -> 158.53428 | G44: -0.014098107 | I44: 39264 | J44: 29.22277 | K44: =SUM(J33:J44) -> 339.44794 | L44: 348.25367 | M44: =(K44-L44)/L44 -> -0.025285379 | O44: 39630 | P44: 0.62 | Q44: =Q43*(1+P44/100) -> 111.4032 | R44: =Q44/Q32-1 -> 0.062354454 | S44: 0.045 | T44: =U44/U32-1 -> 0.063667778 | U44: =U43*W44 -> 112.25664 | V44: 0.53 | W44: =1+V44/100 -> 1.0053 | X44: =SUBSTITUTE(V44,",",".") -> 0.53 | Y44: =SUBSTITUTE(P44,",",".") -> 0.62 | AA44: 39234 | AB44: 59.92048 | AC44: 710.46095 | AD44: 716.99434 | AE44: -0.0091121868
A45: 40026 | B45: 0.0875 | C45: =C44*(1+B45/12) -> 159.69026 | G45: -0.022170326 | I45: 39295 | J45: 31.44926 | K45: =SUM(J34:J45) -> 344.04009 | L45: 350.87992 | M45: =(K45-L45)/L45 -> -0.019493373 | O45: 39661 | P45: 0.2 | Q45: =Q44*(1+P45/100) -> 111.62601 | R45: =Q45/Q33-1 -> 0.060977936 | S45: 0.045 | T45: =U45/U33-1 -> 0.061656263 | U45: =U44*W45 -> 112.57096 | V45: 0.28 | W45: =1+V45/100 -> 1.0028 | X45: =SUBSTITUTE(V45,",",".") -> 0.28 | Y45: =SUBSTITUTE(P45,",",".") -> 0.2 | AA45: 39264 | AB45: 60.70092 | AC45: 715.7506 | AD45: 722.78925 | AE45: -0.0097381817
A46: 40057 | B46: 0.0875 | C46: =C45*(1+B46/12) -> 160.85467 | G46: -0.027040052 | I46: 39326 | J46: 29.12999 | K46: =SUM(J35:J46) -> 347.19429 | L46: 353.59349 | M46: =(K46-L46)/L46 -> -0.018097609 | O46: 39692 | P46: 0.48 | Q46: =Q45*(1+P46/100) -> 112.16182 | R46: =Q46/Q34-1 -> 0.067351452 | S46: 0.045 | T46: =U46/U34-1 -> 0.062504062 | U46: =U45*W46 -> 112.86364 | V46: 0.26 | W46: =1+V46/100 -> 1.0026 | X46: =SUBSTITUTE(V46,",",".") -> 0.26 | Y46: =SUBSTITUTE(P46,",",".") -> 0.48 | AA46: 39295 | AB46: 65.38357 | AC46: 724.24873 | AD46: 728.57646 | AE46: -0.0059399866
A47: 40087 | B47: 0.0875 | C47: =C46*(1+B47/12) -> 162.02757 | G47: -0.030385766 | I47: 39356 | J47: 32.93359 | K47: =SUM(J36:J47) -> 352.71414 | L47: 356.3895 | M47: =(K47-L47)/L47 -> -0.010312753 | O47: 39722 | P47: 0.3 | Q47: =Q46*(1+P47/100) -> 112.4983 | R47: =Q47/Q35-1 -> 0.067990329 | S47: 0.045 | T47: =U47/U35-1 -> 0.064093051 | U47: =U46*W47 -> 113.37153 | V47: 0.45 | W47: =1+V47/100 -> 1.0045 | X47: =SUBSTITUTE(V47,",",".") -> 0.45 | Y47: =SUBSTITUTE(P47,",",".") -> 0.3 | AA47: 39326 | AB47: 60.78764 | AC47: 729.79853 | AD47: 734.353 | AE47: -0.0062020184
A48: 40118 | B48: 0.0875 | C48: =C47*(1+B48/12) -> 163.20902 | G48: -0.030783596 | I48: 39387 | J48: 32.79444 | K48: =SUM(J37:J48) -> 357.9093 | L48: 359.26265 | M48: =(K48-L48)/L48 -> -0.0037670152 | O48: 39753 | P48: 0.73 | Q48: =Q47*(1+P48/100) -> 113.31954 | R48: =Q48/Q36-1 -> 0.069583077 | S48: 0.045 | T48: =U48/U36-1 -> 0.063881038 | U48: =U47*W48 -> 113.77966 | V48: 0.36 | W48: =1+V48/100 -> 1.0036 | X48: =SUBSTITUTE(V48,",",".") -> 0.36 | Y48: =SUBSTITUTE(P48,",",".") -> 0.73 | AA48: 39356 | AB48: 68.50533 | AC48: 740.37784 | AD48: 740.11559 | AE48: 0.00035433371
A49: 40148 | B49: 0.0875 | C49: =C48*(1+B49/12) -> 164.39909 | D49: =C49/C37-1 -> 0.10643476 | G49: -0.024678009 | I49: 39417 | J49: 40.26248 | K49: =SUM(J38:J49) -> 362.22314 | L49: 362.20738 | M49: =(K49-L49)/L49 -> 4.3512721e-05 | O49: 39783 | P49: 0.14 | Q49: =Q48*(1+P49/100) -> 113.47819 | R49: =Q49/Q37-1 -> 0.0656457 | S49: 0.045 | T49: =U49/U37-1 -> 0.059023134 | U49: =U48*W49 -> 114.09825 | V49: 0.28 | W49: =1+V49/100 -> 1.0028 | X49: =SUBSTITUTE(V49,",",".") -> 0.28 | Y49: =SUBSTITUTE(P49,",",".") -> 0.14 | AA49: 39387 | AB49: 67.89832 | AC49: 749.91656 | AD49: 745.86065 | AE49: 0.00543789
A50: 40179 | B50: 0.0875 | C50: =C49*(1+B50/12) -> 165.59783 | G50: -0.026052135 | I50: 39448 | J50: 30.42878 | K50: =SUM(J39:J50) -> 366.25866 | L50: 365.21804 | M50: =(K50-L50)/L50 -> 0.0028493203 | O50: 39814 | P50: 0.24 | Q50: =Q49*(1+P50/100) -> 113.75053 | R50: =Q50/Q38-1 -> 0.066922942 | S50: 0.045 | T50: =U50/U38-1 -> 0.058391133 | U50: =U49*W50 -> 114.64592 | V50: 0.48 | W50: =1+V50/100 -> 1.0048 | X50: =SUBSTITUTE(V50,",",".") -> 0.48 | Y50: =SUBSTITUTE(P50,",",".") -> 0.24 | AA50: 39417 | AB50: 83.3337 | AC50: 756.85381 | AD50: 751.58461 | AE50: 0.0070107851
A51: 40210 | B51: 0.0875 | C51: =C50*(1+B51/12) -> 166.80531 | G51: -0.02653707 | I51: 39479 | J51: 29.08361 | K51: =SUM(J40:J51) -> 371.63936 | L51: 368.28897 | M51: =(K51-L51)/L51 -> 0.0090971865 | O51: 39845 | P51: 0.39 | Q51: =Q50*(1+P51/100) -> 114.19416 | R51: =Q51/Q39-1 -> 0.067241871 | S51: 0.045 | T51: =U51/U39-1 -> 0.059023071 | U51: =U50*W51 -> 115.27647 | V51: 0.55 | W51: =1+V51/100 -> 1.0055 | X51: =SUBSTITUTE(V51,",",".") -> 0.55 | Y51: =SUBSTITUTE(P51,",",".") -> 0.39 | AA51: 39448 | AB51: 62.7821 | AC51: 763.79106 | AD51: 757.28419 | AE51: 0.0085923813
A52: 40238 | B52: 0.0875 | C52: =C51*(1+B52/12) -> 168.0216 | G52: -0.01928169 | I52: 39508 | J52: 33.16552 | K52: =SUM(J41:J52) -> 375.90681 | L52: 371.41459 | M52: =(K52-L52)/L52 -> 0.012094901 | O52: 39873 | P52: 0.15 | Q52: =Q51*(1+P52/100) -> 114.36545 | R52: =Q52/Q40-1 -> 0.061096728 | S52: 0.045 | T52: =U52/U40-1 -> 0.056071972 | U52: =U51*W52 -> 115.50702 | V52: 0.2 | W52: =1+V52/100 -> 1.002 | X52: =SUBSTITUTE(V52,",",".") -> 0.2 | Y52: =SUBSTITUTE(P52,",",".") -> 0.15 | AA52: 39479 | AB52: 60.35406 | AC52: 773.76335 | AD52: 762.95645 | AE52: 0.014164501
A53: 40269 | B53: 0.088 | C53: =C52*(1+B53/12) -> 169.25376 | G53: -0.017818731 | I53: 39539 | J53: 33.81491 | K53: =SUM(J42:J53) -> 381.47305 | L53: 374.58955 | M53: =(K53-L53)/L53 -> 0.018376112 | O53: 39904 | P53: 0.91 | Q53: =Q52*(1+P53/100) -> 115.40618 | R53: =Q53/Q41-1 -> 0.061096728 | S53: 0.045 | T53: =U53/U41-1 -> 0.055336765 | U53: =U52*W53 -> 116.06146 | V53: 0.48 | W53: =1+V53/100 -> 1.0048 | X53: =SUBSTITUTE(V53,",",".") -> 0.48 | Y53: =SUBSTITUTE(P53,",",".") -> 0.91 | AA53: marÃ§o 2008 | AB53: 68.07175 | AC53: 780.87403 | AD53: 768.59894 | AE53: 0.015970731
A54: 40299 | B54: 0.095 | C54: =C53*(1+B54/12) -> 170.59369 | G54: -0.016824346 | I54: 39569 | J54: 35.20647 | K54: =SUM(J43:J54) -> 386.11158 | L54: 377.80882 | M54: =(K54-L54)/L54 -> 0.02197609 | O54: 39934 | P54: 0.65 | Q54: =Q53*(1+P54/100) -> 116.15632 | R54: =Q54/Q42-1 -> 0.058572561 | S54: 0.045 | T54: =U54/U42-1 -> 0.051986157 | U54: =U53*W54 -> 116.60695 | V54: 0.47 | W54: =1+V54/100 -> 1.0047 | X54: =SUBSTITUTE(V54,",",".") -> 0.47 | Y54: =SUBSTITUTE(P54,",",".") -> 0.65 | AA54: 39539 | AB54: 68.85219 | AC54: 790.49946 | AD54: 774.20994 | AE54: 0.021040184
A55: 40330 | B55: 0.10025 | C55: =C54*(1+B55/12) -> 172.01885 | G55: -0.017851618 | I55: 39600 | J55: 34.41792 | K55: =SUM(J44:J55) -> 391.90974 | L55: 381.06784 | M55: =(K55-L55)/L55 -> 0.028451377 | O55: 39965 | P55: 0.13 | Q55: =Q54*(1+P55/100) -> 116.30732 | R55: =Q55/Q43-1 -> 0.050494257 | S55: 0.045 | T55: =U55/U43-1 -> 0.048017975 | U55: =U54*W55 -> 117.02673 | V55: 0.36 | W55: =1+V55/100 -> 1.0036 | X55: =SUBSTITUTE(V55,",",".") -> 0.36 | Y55: =SUBSTITUTE(P55,",",".") -> 0.13 | AA55: 39569 | AB55: 71.1068 | AC55: 797.69686 | AD55: 779.78858 | AE55: 0.022965561
A56: 40360 | B56: 0.1041129 | C56: =C55*(1+B56/12) -> 173.5113 | G56: -0.013830695 | I56: 39630 | J56: 35.48479 | K56: =SUM(J45:J56) -> 398.17176 | L56: 384.36262 | M56: =(K56-L56)/L56 -> 0.035927383 | O56: 39995 | P56: 0.12 | Q56: =Q55*(1+P56/100) -> 116.44689 | R56: =Q56/Q44-1 -> 0.04527415 | S56: 0.045 | T56: =U56/U44-1 -> 0.044994746 | U56: =U55*W56 -> 117.3076 | V56: 0.24 | W56: =1+V56/100 -> 1.0024 | X56: =SUBSTITUTE(V56,",",".") -> 0.24 | Y56: =SUBSTITUTE(P56,",",".") -> 0.12 | AA56: 39600 | AB56: 69.02562 | AC56: 806.802 | AD56: 785.33512 | AE56: 0.027334674
A57: 40391 | B57: 0.1075 | C57: =C56*(1+B57/12) -> 175.06567 | G57: -0.0085602471 | I57: 39661 | J57: 35.02093 | K57: =SUM(J46:J57) -> 401.74343 | L57: 387.68993 | M57: =(K57-L57)/L57 -> 0.036249318 | O57: 40026 | P57: 0.03 | Q57: =Q56*(1+P57/100) -> 116.48182 | R57: =Q57/Q45-1 -> 0.043500731 | S57: 0.045 | T57: =U57/U45-1 -> 0.043640046 | U57: =U56*W57 -> 117.48356 | V57: 0.15 | W57: =1+V57/100 -> 1.0015 | X57: =SUBSTITUTE(V57,",",".") -> 0.15 | Y57: =SUBSTITUTE(P57,",",".") -> 0.03 | AA57: 39630 | AB57: 70.5865 | AC57: 816.68758 | AD57: 790.85108 | AE57: 0.032669238
A58: 40422 | B58: 0.1075 | C58: =C57*(1+B58/12) -> 176.63397 | G58: -0.0082717649 | I58: 39692 | J58: 34.83539 | K58: =SUM(J47:J58) -> 407.44883 | L58: 391.04752 | M58: =(K58-L58)/L58 -> 0.041941994 | O58: 40057 | P58: 0.26 | Q58: =Q57*(1+P58/100) -> 116.78468 | R58: =Q58/Q46-1 -> 0.041215996 | S58: 0.045 | T58: =U58/U46-1 -> 0.043431859 | U58: =U57*W58 -> 117.76552 | V58: 0.24 | W58: =1+V58/100 -> 1.0024 | X58: =SUBSTITUTE(V58,",",".") -> 0.24 | Y58: =SUBSTITUTE(P58,",",".") -> 0.26 | AA58: 39661 | AB58: 69.28577 | AC58: 820.58978 | AD58: 796.33945 | AE58: 0.030452253
A59: 40452 | B59: 0.1075 | C59: =C58*(1+B59/12) -> 178.21632 | G59: -0.0057249724 | I59: 39722 | J59: 36.0878 | K59: =SUM(J48:J59) -> 410.60304 | L59: 394.43407 | M59: =(K59-L59)/L59 -> 0.040992829 | O59: 40087 | P59: 0.14 | Q59: =Q58*(1+P59/100) -> 116.94817 | R59: =Q59/Q47-1 -> 0.039555033 | S59: 0.045 | T59: =U59/U47-1 -> 0.041665971 | U59: =U58*W59 -> 118.09526 | V59: 0.28 | W59: =1+V59/100 -> 1.0028 | X59: =SUBSTITUTE(V59,",",".") -> 0.28 | Y59: =SUBSTITUTE(P59,",",".") -> 0.14 | AA59: 39692 | AB59: 68.85219 | AC59: 828.65433 | AD59: 801.80503 | AE59: 0.033486071
A60: 40483 | B60: 0.1075 | C60: =C59*(1+B60/12) -> 179.81284 | G60: 0.0014585288 | I60: 39753 | J60: 33.90769 | K60: =SUM(J49:J60) -> 411.71629 | L60: 397.84944 | M60: =(K60-L60)/L60 -> 0.034854515 | O60: 40118 | P60: 0.6 | Q60: =Q59*(1+P60/100) -> 117.64986 | R60: =Q60/Q48-1 -> 0.038213406 | S60: 0.045 | T60: =U60/U48-1 -> 0.042184936 | U60: =U59*W60 -> 118.57945 | V60: 0.41 | W60: =1+V60/100 -> 1.0041 | X60: =SUBSTITUTE(V60,",",".") -> 0.41 | Y60: =SUBSTITUTE(P60,",",".") -> 0.6 | AA60: 39722 | AB60: 71.19351 | AC60: 831.34251 | AD60: 807.2543 | AE60: 0.029839685
A61: 40513 | B61: 0.1075 | C61: =C60*(1+B61/12) -> 181.42366 | D61: =C61/C49-1 -> 0.10355639 | G61: 0.0095392833 | I61: 39783 | J61: 42.25705 | K61: =SUM(J50:J61) -> 413.71086 | L61: 401.29459 | M61: =(K61-L61)/L61 -> 0.030940531 | O61: 40148 | P61: 0.03 | Q61: =Q60*(1+P61/100) -> 117.68516 | R61: =Q61/Q49-1 -> 0.037072967 | S61: 0.045 | T61: =U61/U49-1 -> 0.043120283 | U61: =U60*W61 -> 119.0182 | V61: 0.37 | W61: =1+V61/100 -> 1.0037 | X61: =SUBSTITUTE(V61,",",".") -> 0.37 | Y61: =SUBSTITUTE(P61,",",".") -> 0.03 | AA61: 39753 | AB61: 66.07729 | AC61: 829.52148 | AD61: 812.69559 | AE61: 0.020703803
A62: 40544 | B62: 0.10943548 | C62: =C61*(1+B62/12) -> 183.07818 | G62: 0.010604106 | I62: 39814 | J62: 31.9595 | K62: =SUM(J51:J62) -> 415.24158 | L62: 404.77146 | M62: =(K62-L62)/L62 -> 0.025866754 | O62: 40179 | P62: 0.55 | Q62: =Q61*(1+P62/100) -> 118.33243 | R62: =Q62/Q50-1 -> 0.040280196 | S62: 0.045 | T62: =U62/U50-1 -> 0.045923254 | U62: =U61*W62 -> 119.91083 | V62: 0.75 | W62: =1+V62/100 -> 1.0075 | X62: =SUBSTITUTE(V62,",",".") -> 0.75 | Y62: =SUBSTITUTE(P62,",",".") -> 0.55 | AA62: 39783 | AB62: 83.07355 | AC62: 829.26133 | AD62: 818.13893 | AE62: 0.013594757
A63: 40575 | B63: 0.1125 | C63: =C62*(1+B63/12) -> 184.79453 | G63: 0.014592449 | I63: 39845 | J63: 29.54746 | K63: =SUM(J52:J63) -> 415.70543 | L63: 408.28283 | M63: =(K63-L63)/L63 -> 0.018180055 | O63: 40210 | P63: 0.74 | Q63: =Q62*(1+P63/100) -> 119.20809 | R63: =Q63/Q51-1 -> 0.043907032 | S63: 0.045 | T63: =U63/U51-1 -> 0.048315719 | U63: =U62*W63 -> 120.84614 | V63: 0.78 | W63: =1+V63/100 -> 1.0078 | X63: =SUBSTITUTE(V63,",",".") -> 0.78 | Y63: =SUBSTITUTE(P63,",",".") -> 0.74 | AA63: 39814 | AB63: 63.38911 | AC63: 829.86834 | AD63: 823.5955 | AE63: 0.0076164122
A64: 40603 | B64: 0.11717742 | C64: =C63*(1+B64/12) -> 186.59901 | G64: 0.007918485 | I64: 39873 | J64: 35.62394 | K64: =SUM(J53:J64) -> 418.16385 | L64: 411.83222 | M64: =(K64-L64)/L64 -> 0.015374296 | O64: 40238 | P64: 0.8 | Q64: =Q63*(1+P64/100) -> 120.16175 | R64: =Q64/Q52-1 -> 0.050682265 | S64: 0.045 | T64: =U64/U52-1 -> 0.051663633 | U64: =U63*W64 -> 121.47454 | V64: 0.52 | W64: =1+V64/100 -> 1.0052 | X64: =SUBSTITUTE(V64,",",".") -> 0.52 | Y64: =SUBSTITUTE(P64,",",".") -> 0.8 | AA64: 39845 | AB64: 58.8799 | AC64: 828.39418 | AD64: 829.07725 | AE64: -0.00082388996
A65: 40634 | B65: 0.118 | C65: =C64*(1+B65/12) -> 188.4339 | G65: 0.0088253612 | I65: 39904 | J65: 33.90769 | K65: =SUM(J54:J65) -> 418.25663 | L65: 415.42367 | M65: =(K65-L65)/L65 -> 0.0068194406 | O65: 40269 | P65: 0.56 | Q65: =Q64*(1+P65/100) -> 120.83466 | R65: =Q65/Q53-1 -> 0.04703804 | S65: 0.045 | T65: =U65/U53-1 -> 0.052605609 | U65: =U64*W65 -> 122.16694 | V65: 0.57 | W65: =1+V65/100 -> 1.0057 | X65: =SUBSTITUTE(V65,",",".") -> 0.57 | Y65: =SUBSTITUTE(P65,",",".") -> 0.56 | AA65: marÃ§o 2009 | AB65: 71.45366 | AC65: 831.77609 | AD65: 834.59658 | AE65: -0.0033794598
A66: 40664 | B66: 0.12 | C66: =C65*(1+B66/12) -> 190.31824 | G66: 0.0099479789 | I66: 39934 | J66: 35.85587 | K66: =SUM(J55:J66) -> 418.90603 | L66: 419.06166 | M66: =(K66-L66)/L66 -> -0.00037137894 | O66: 40299 | P66: 0.06 | Q66: =Q65*(1+P66/100) -> 120.90716 | R66: =Q66/Q54-1 -> 0.04090041 | S66: 0.045 | T66: =U66/U54-1 -> 0.052186536 | U66: =U65*W66 -> 122.69226 | V66: 0.43 | W66: =1+V66/100 -> 1.0043 | X66: =SUBSTITUTE(V66,",",".") -> 0.43 | Y66: =SUBSTITUTE(P66,",",".") -> 0.06 | AA66: 39904 | AB66: 66.85773 | AC66: 829.78163 | AD66: 840.16582 | AE66: -0.012359695
A67: 40695 | B67: 0.12183333 | C67: =C66*(1+B67/12) -> 192.2505 | G67: 0.010498519 | I67: 39965 | J67: 36.36611 | K67: =SUM(J56:J67) -> 420.85422 | L67: 422.75085 | M67: =(K67-L67)/L67 -> -0.0044864115 | O67: 40330 | P67: -0.15 | Q67: =Q66*(1+P67/100) -> 120.7258 | R67: =Q67/Q55-1 -> 0.037989673 | S67: 0.045 | T67: =U67/U55-1 -> 0.048412252 | U67: =U66*W67 -> 122.69226 | V67: 0 | W67: =1+V67/100 -> 1 | X67: =SUBSTITUTE(V67,",",".") -> 0 | Y67: =SUBSTITUTE(P67,",",".") -> -0.15 | AA67: 39934 | AB67: 71.1068 | AC67: 829.78163 | AD67: 845.79714 | AE67: -0.018935403
A68: 40725 | B68: 0.1233871 | C68: =C67*(1+B68/12) -> 194.22727 | G68: 0.0082430165 | I68: 39995 | J68: 35.1137 | K68: =SUM(J57:J68) -> 420.48313 | L68: 426.49591 | M68: =(K68-L68)/L68 -> -0.014098107 | O68: 40360 | P68: 0.18 | Q68: =Q67*(1+P68/100) -> 120.9431 | R68: =Q68/Q56-1 -> 0.03861172 | S68: 0.045 | T68: =U68/U56-1 -> 0.046006677 | U68: =U67*W68 -> 122.70453 | V68: 0.01 | W68: =1+V68/100 -> 1.0001 | X68: =SUBSTITUTE(V68,",",".") -> 0.01 | Y68: =SUBSTITUTE(P68,",",".") -> 0.18 | AA68: 39965 | AB68: 72.92782 | AC68: 833.68383 | AD68: 851.50195 | AE68: -0.020925521
A69: 40756 | B69: 0.125 | C69: =C68*(1+B69/12) -> 196.25047 | G69: 0.0067015975 | I69: 40026 | J69: 35.29925 | K69: =SUM(J58:J69) -> 420.76145 | L69: 430.30137 | M69: =(K69-L69)/L69 -> -0.022170326 | O69: 40391 | P69: 0.24 | Q69: =Q68*(1+P69/100) -> 121.23337 | R69: =Q69/Q57-1 -> 0.040792151 | S69: 0.045 | T69: =U69/U57-1 -> 0.044857793 | U69: =U68*W69 -> 122.75361 | V69: 0.04 | W69: =1+V69/100 -> 1.0004 | X69: =SUBSTITUTE(V69,",",".") -> 0.04 | Y69: =SUBSTITUTE(P69,",",".") -> 0.24 | AA69: 39995 | AB69: 69.80606 | AC69: 832.90339 | AD69: 857.29058 | AE69: -0.028446814
A70: 40787 | B70: 0.12 | C70: =C69*(1+B70/12) -> 198.21298 | G70: 0.0040705801 | I70: 40057 | J70: 36.50526 | K70: =SUM(J59:J70) -> 422.43132 | L70: 434.17134 | M70: =(K70-L70)/L70 -> -0.027040052 | O70: 40422 | P70: 0.19 | Q70: =Q69*(1+P70/100) -> 121.46371 | R70: =Q70/Q58-1 -> 0.040065485 | S70: 0.045 | T70: =U70/U58-1 -> 0.047046741 | U70: =U69*W70 -> 123.306 | V70: 0.45 | W70: =1+V70/100 -> 1.0045 | X70: =SUBSTITUTE(V70,",",".") -> 0.45 | Y70: =SUBSTITUTE(P70,",",".") -> 0.19 | AA70: 40026 | AB70: 70.49979 | AC70: 834.11741 | AD70: 863.17209 | AE70: -0.033660354
A71: 40817 | B71: 0.11806452 | C71: =C70*(1+B71/12) -> 200.16314 | G71: -0.00037627588 | I71: 40087 | J71: 38.45345 | K71: =SUM(J60:J71) -> 424.79697 | L71: 438.10926 | M71: =(K71-L71)/L71 -> -0.030385766 | O71: 40452 | P71: 0.63 | Q71: =Q70*(1+P71/100) -> 122.22893 | R71: =Q71/Q59-1 -> 0.045154681 | S71: 0.045 | T71: =U71/U59-1 -> 0.05195412 | U71: =U70*W71 -> 124.2308 | V71: 0.75 | W71: =1+V71/100 -> 1.0075 | X71: =SUBSTITUTE(V71,",",".") -> 0.75 | Y71: =SUBSTITUTE(P71,",",".") -> 0.63 | AA71: 40057 | AB71: 73.44812 | AC71: 838.71334 | AD71: 869.15387 | AE71: -0.035023182
A72: 40848 | B72: 0.115 | C72: =C71*(1+B72/12) -> 202.08137 | G72: -0.0048303609 | I72: 40118 | J72: 37.61851 | K72: =SUM(J61:J72) -> 428.50779 | L72: 442.11776 | M72: =(K72-L72)/L72 -> -0.030783596 | O72: 40483 | P72: 0.66 | Q72: =Q71*(1+P72/100) -> 123.03564 | R72: =Q72/Q60-1 -> 0.045778034 | S72: 0.045 | T72: =U72/U60-1 -> 0.056354287 | U72: =U71*W72 -> 125.26191 | V72: 0.83 | W72: =1+V72/100 -> 1.0083 | X72: =SUBSTITUTE(V72,",",".") -> 0.83 | Y72: =SUBSTITUTE(P72,",",".") -> 0.66 | AA72: 40087 | AB72: 76.65659 | AC72: 844.17642 | AD72: 875.2413 | AE72: -0.035492933
A73: 40878 | B73: 0.11 | C73: =C72*(1+B73/12) -> 203.93378 | D73: =C73/C61-1 -> 0.12407487 | G73: -0.0052264711 | I73: 40148 | J73: 48.93654 | K73: =SUM(J62:J73) -> 435.18728 | L73: 446.19857 | M73: =(K73-L73)/L73 -> -0.024678009 | O73: 40513 | P73: 0.56 | Q73: =Q72*(1+P73/100) -> 123.72464 | R73: =Q73/Q61-1 -> 0.051318995 | S73: 0.045 | T73: =U73/U61-1 -> 0.059090683 | U73: =U72*W73 -> 126.05106 | V73: 0.63 | W73: =1+V73/100 -> 1.0063 | X73: =SUBSTITUTE(V73,",",".") -> 0.63 | Y73: =SUBSTITUTE(P73,",",".") -> 0.56 | AA73: 40118 | AB73: 74.83557 | AC73: 852.9347 | AD73: 881.43762 | AE73: -0.032336855
A74: 40909 | B74: 0.10790323 | C74: =C73*(1+B74/12) -> 205.76754 | G74: -0.0055298073 | I74: 40179 | J74: 35.39202 | K74: =SUM(J63:J74) -> 438.6198 | L74: 450.35244 | M74: =(K74-L74)/L74 -> -0.026052135 | O74: 40544 | P74: 0.47 | Q74: =Q73*(1+P74/100) -> 124.30615 | R74: =Q74/Q62-1 -> 0.050482541 | S74: 0.045 | T74: =U74/U62-1 -> 0.059931649 | U74: =U73*W74 -> 127.09729 | V74: 0.83 | W74: =1+V74/100 -> 1.0083 | X74: =SUBSTITUTE(V74,",",".") -> 0.83 | Y74: =SUBSTITUTE(P74,",",".") -> 0.47 | AA74: 40148 | AB74: 97.55506 | AC74: 867.41621 | AD74: 887.74393 | AE74: -0.022898177
A75: 40940 | B75: 0.105 | C75: =C74*(1+B75/12) -> 207.568 | G75: -0.01160279 | I75: 40210 | J75: 33.44383 | K75: =SUM(J64:J75) -> 442.51617 | L75: 454.57937 | M75: =(K75-L75)/L75 -> -0.02653707 | O75: 40575 | P75: 0.83 | Q75: =Q74*(1+P75/100) -> 125.33789 | R75: =Q75/Q63-1 -> 0.05142103 | S75: 0.045 | T75: =U75/U63-1 -> 0.060141994 | U75: =U74*W75 -> 128.11406 | V75: 0.8 | W75: =1+V75/100 -> 1.008 | X75: =SUBSTITUTE(V75,",",".") -> 0.8 | Y75: =SUBSTITUTE(P75,",",".") -> 0.83 | AA75: 40179 | AB75: 69.89278 | AC75: 873.91988 | AD75: 894.15934 | AE75: -0.022635181
A76: 40969 | B76: 0.099193548 | C76: =C75*(1+B76/12) -> 209.28379 | G76: -0.011019134 | I76: 40238 | J76: 43.13837 | K76: =SUM(J65:J76) -> 450.0306 | L76: 458.87855 | M76: =(K76-L76)/L76 -> -0.01928169 | O76: 40603 | P76: 0.75 | Q76: =Q75*(1+P76/100) -> 126.27792 | R76: =Q76/Q64-1 -> 0.050899492 | S76: 0.045 | T76: =U76/U64-1 -> 0.06298957 | U76: =U75*W76 -> 129.12617 | V76: 0.79 | W76: =1+V76/100 -> 1.0079 | X76: =SUBSTITUTE(V76,",",".") -> 0.79 | Y76: =SUBSTITUTE(P76,",",".") -> 0.75 | AA76: 40210 | AB76: 65.557 | AC76: 880.59698 | AD76: 900.68156 | AE76: -0.022299311
A77: 41000 | B77: 0.0945 | C77: =C76*(1+B77/12) -> 210.9319 | G77: -0.016112364 | I77: 40269 | J77: 38.87092 | K77: =SUM(J66:J77) -> 454.99383 | L77: 463.24833 | M77: =(K77-L77)/L77 -> -0.017818731 | O77: 40634 | P77: 1.04 | Q77: =Q76*(1+P77/100) -> 127.59121 | R77: =Q77/Q65-1 -> 0.055915719 | S77: 0.045 | T77: =U77/U65-1 -> 0.0651035 | U77: =U76*W77 -> 130.12044 | V77: 0.77 | W77: =1+V77/100 -> 1.0077 | X77: =SUBSTITUTE(V77,",",".") -> 0.77 | Y77: =SUBSTITUTE(P77,",",".") -> 1.04 | AA77: marÃ§o 2010 | AB77: 85.06801 | AC77: 894.21133 | AD77: 907.30688 | AE77: -0.014433435
A78: 41030 | B78: 0.08983871 | C78: =C77*(1+B78/12) -> 212.51105 | G78: -0.018477993 | I78: 40299 | J78: 40.67995 | K78: =SUM(J67:J78) -> 459.81791 | L78: 467.68643 | M78: =(K78-L78)/L78 -> -0.016824346 | O78: 40664 | P78: 0.5 | Q78: =Q77*(1+P78/100) -> 128.22917 | R78: =Q78/Q66-1 -> 0.060558962 | S78: 0.045 | T78: =U78/U66-1 -> 0.065527717 | U78: =U77*W78 -> 130.732 | V78: 0.47 | W78: =1+V78/100 -> 1.0047 | X78: =SUBSTITUTE(V78,",",".") -> 0.47 | Y78: =SUBSTITUTE(P78,",",".") -> 0.5 | AA78: 40269 | AB78: 74.92228 | AC78: 902.27588 | AD78: 914.03022 | AE78: -0.012859906
A79: 41061 | B79: 0.085 | C79: =C78*(1+B79/12) -> 214.01634 | G79: -0.017076137 | I79: 40330 | J79: 40.30886 | K79: =SUM(J68:J79) -> 463.76066 | L79: 472.19002 | M79: =(K79-L79)/L79 -> -0.017851618 | O79: 40695 | P79: 0.14 | Q79: =Q78*(1+P79/100) -> 128.40869 | R79: =Q79/Q67-1 -> 0.063639203 | S79: 0.045 | T79: =U79/U67-1 -> 0.067126009 | U79: =U78*W79 -> 130.9281 | V79: 0.15 | W79: =1+V79/100 -> 1.0015 | X79: =SUBSTITUTE(V79,",",".") -> 0.15 | Y79: =SUBSTITUTE(P79,",",".") -> 0.14 | AA79: 40299 | AB79: 78.21748 | AC79: 909.38656 | AD79: 920.84557 | AE79: -0.012444004
A80: 41091 | B80: 0.081774194 | C80: =C79*(1+B80/12) -> 215.47476 | G80: -0.017690777 | I80: 40360 | J80: 41.51488 | K80: =SUM(J69:J80) -> 470.16184 | L80: 476.7557 | M80: =(K80-L80)/L80 -> -0.013830695 | O80: 40725 | P80: 0.2 | Q80: =Q79*(1+P80/100) -> 128.66551 | R80: =Q80/Q68-1 -> 0.063851549 | S80: 0.045 | T80: =U80/U68-1 -> 0.068726538 | U80: =U79*W80 -> 131.13759 | V80: 0.16 | W80: =1+V80/100 -> 1.0016 | X80: =SUBSTITUTE(V80,",",".") -> 0.16 | Y80: =SUBSTITUTE(P80,",",".") -> 0.2 | AA80: 40330 | AB80: 78.13076 | AC80: 914.5895 | AD80: 927.74609 | AE80: -0.014181245
A81: 41122 | B81: 0.079677419 | C81: =C80*(1+B81/12) -> 216.90546 | G81: -0.011901621 | I81: 40391 | J81: 42.3962 | K81: =SUM(J70:J81) -> 477.25879 | L81: 481.37952 | M81: =(K81-L81)/L81 -> -0.0085602471 | O81: 40756 | P81: 0.14 | Q81: =Q80*(1+P81/100) -> 128.84564 | R81: =Q81/Q69-1 -> 0.062790244 | S81: 0.045 | T81: =U81/U69-1 -> 0.072251925 | U81: =U80*W81 -> 131.62279 | V81: 0.37 | W81: =1+V81/100 -> 1.0037 | X81: =SUBSTITUTE(V81,",",".") -> 0.37 | Y81: =SUBSTITUTE(P81,",",".") -> 0.14 | AA81: 40360 | AB81: 80.5588 | AC81: 925.34224 | AD81: 934.72419 | AE81: -0.010037132
A82: 41153 | B82: 0.075 | C82: =C81*(1+B82/12) -> 218.26112 | G82: -0.015828 | I82: 40422 | J82: 41.28295 | K82: =SUM(J71:J82) -> 482.03648 | L82: 486.05703 | M82: =(K82-L82)/L82 -> -0.0082717649 | O82: 40787 | P82: 0.51 | Q82: =Q81*(1+P82/100) -> 129.50275 | R82: =Q82/Q70-1 -> 0.066184724 | S82: 0.045 | T82: =U82/U70-1 -> 0.073105884 | U82: =U81*W82 -> 132.3204 | V82: 0.53 | W82: =1+V82/100 -> 1.0053 | X82: =SUBSTITUTE(V82,",",".") -> 0.53 | Y82: =SUBSTITUTE(P82,",",".") -> 0.51 | AA82: 40391 | AB82: 82.46654 | AC82: 937.30899 | AD82: 941.77132 | AE82: -0.0047382317
A83: 41183 | B83: 0.073306452 | C83: =C82*(1+B83/12) -> 219.59445 | G83: -0.010102197 | I83: 40452 | J83: 44.39077 | K83: =SUM(J72:J83) -> 487.9738 | L83: 490.78352 | M83: =(K83-L83)/L83 -> -0.0057249724 | O83: 40817 | P83: 0.98 | Q83: =Q82*(1+P83/100) -> 130.77188 | R83: =Q83/Q71-1 -> 0.069893008 | S83: 0.045 | T83: =U83/U71-1 -> 0.069697508 | U83: =U82*W83 -> 132.88937 | V83: 0.43 | W83: =1+V83/100 -> 1.0043 | X83: =SUBSTITUTE(V83,",",".") -> 0.43 | Y83: =SUBSTITUTE(P83,",",".") -> 0.98 | AA83: 40422 | AB83: 80.38537 | AC83: 944.24624 | AD83: 948.87831 | AE83: -0.0048816219
A84: 41214 | B84: 0.0725 | C84: =C83*(1+B84/12) -> 220.92117 | G84: -0.009151977 | I84: 40483 | J84: 45.92149 | K84: =SUM(J73:J84) -> 496.27678 | L84: 495.554 | M84: =(K84-L84)/L84 -> 0.0014585288 | O84: 40848 | P84: 0.58 | Q84: =Q83*(1+P84/100) -> 131.53036 | R84: =Q84/Q72-1 -> 0.069042706 | S84: 0.045 | T84: =U84/U72-1 -> 0.066408743 | U84: =U83*W84 -> 133.5804 | V84: 0.52 | W84: =1+V84/100 -> 1.0052 | X84: =SUBSTITUTE(V84,",",".") -> 0.52 | Y84: =SUBSTITUTE(P84,",",".") -> 0.58 | AA84: 40452 | AB84: 85.67502 | AC84: 953.26467 | AD84: 956.03565 | AE84: -0.0028984069
A85: 41244 | B85: 0.0725 | C85: =C84*(1+B85/12) -> 222.2559 | D85: =C85/C73-1 -> 0.08984348 | G85: -0.010303379 | I85: 40513 | J85: 57.79614 | K85: =SUM(J74:J85) -> 505.13638 | L85: 500.36327 | M85: =(K85-L85)/L85 -> 0.0095392833 | O85: 40878 | P85: 0.19 | Q85: =Q84*(1+P85/100) -> 131.78026 | R85: =Q85/Q73-1 -> 0.065109275 | S85: 0.045 | T85: =U85/U73-1 -> 0.06503109 | U85: =U84*W85 -> 134.2483 | V85: 0.5 | W85: =1+V85/100 -> 1.005 | X85: =SUBSTITUTE(V85,",",".") -> 0.5 | Y85: =SUBSTITUTE(P85,",",".") -> 0.19 | AA85: 40483 | AB85: 88.44992 | AC85: 966.87902 | AD85: 963.23354 | AE85: 0.0037846248
A86: 41275 | B86: 0.0725 | C86: =C85*(1+B86/12) -> 223.5987 | G86: -0.0096234803 | I86: 40544 | J86: 40.8191 | K86: =SUM(J75:J86) -> 510.56346 | L86: 505.2062 | M86: =(K86-L86)/L86 -> 0.010604106 | O86: 40909 | P86: 0.31 | Q86: =Q85*(1+P86/100) -> 132.18878 | R86: =Q86/Q74-1 -> 0.063413072 | S86: 0.045 | T86: =U86/U74-1 -> 0.062179177 | U86: =U85*W86 -> 135.00009 | V86: 0.56 | W86: =1+V86/100 -> 1.0056 | X86: =SUBSTITUTE(V86,",",".") -> 0.56 | Y86: =SUBSTITUTE(P86,",",".") -> 0.31 | AA86: 40513 | AB86: 110.90926 | AC86: 980.23322 | AD86: 970.46197 | AE86: 0.010068653
A87: 41306 | B87: 0.0725 | C87: =C86*(1+B87/12) -> 224.9496 | G87: -0.011722917 | I87: 40575 | J87: 40.40163 | K87: =SUM(J76:J87) -> 517.52126 | L87: 510.07797 | M87: =(K87-L87)/L87 -> 0.014592449 | O87: 40940 | P87: 0.44 | Q87: =Q86*(1+P87/100) -> 132.77041 | R87: =Q87/Q75-1 -> 0.0592999 | S87: 0.045 | T87: =U87/U75-1 -> 0.058491055 | U87: =U86*W87 -> 135.60759 | V87: 0.45 | W87: =1+V87/100 -> 1.0045 | X87: =SUBSTITUTE(V87,",",".") -> 0.45 | Y87: =SUBSTITUTE(P87,",",".") -> 0.44 | AA87: 40544 | AB87: 77.2636 | AC87: 987.60404 | AD87: 977.71119 | AE87: 0.010118373
A88: 41334 | B88: 0.0725 | C88: =C87*(1+B88/12) -> 226.30867 | G88: -0.0099946753 | I88: 40603 | J88: 44.66908 | K88: =SUM(J77:J88) -> 519.05197 | L88: 514.97415 | M88: =(K88-L88)/L88 -> 0.007918485 | O88: 40969 | P88: 0.23 | Q88: =Q87*(1+P88/100) -> 133.07579 | R88: =Q88/Q76-1 -> 0.053832546 | S88: 0.045 | T88: =U88/U76-1 -> 0.052399927 | U88: =U87*W88 -> 135.89237 | V88: 0.21 | W88: =1+V88/100 -> 1.0021 | X88: =SUBSTITUTE(V88,",",".") -> 0.21 | Y88: =SUBSTITUTE(P88,",",".") -> 0.23 | AA88: 40575 | AB88: 76.65659 | AC88: 998.70363 | AD88: 984.97213 | AE88: 0.013941009
A89: 41365 | B89: 0.073583333 | C89: =C88*(1+B89/12) -> 227.69639 | G89: -0.0053059324 | I89: 40634 | J89: 44.298 | K89: =SUM(J78:J89) -> 524.47905 | L89: 519.89083 | M89: =(K89-L89)/L89 -> 0.0088253612 | O89: 41000 | P89: 0.78 | Q89: =Q88*(1+P89/100) -> 134.11378 | R89: =Q89/Q77-1 -> 0.051120784 | S89: 0.045 | T89: =U89/U77-1 -> 0.051042261 | U89: =U88*W89 -> 136.76208 | V89: 0.64 | W89: =1+V89/100 -> 1.0064 | X89: =SUBSTITUTE(V89,",",".") -> 0.64 | Y89: =SUBSTITUTE(P89,",",".") -> 0.78 | AA89: marÃ§o 2011 | AB89: 84.28757 | AC89: 997.92319 | AD89: 992.23638 | AE89: 0.0057313051
A90: 41395 | B90: 0.075322581 | C90: =C89*(1+B90/12) -> 229.12561 | G90: -0.0052311207 | I90: 40664 | J90: 46.24619 | K90: =SUM(J79:J90) -> 530.04529 | L90: 524.82435 | M90: =(K90-L90)/L90 -> 0.0099479789 | O90: 41030 | P90: 0.43 | Q90: =Q89*(1+P90/100) -> 134.69047 | R90: =Q90/Q78-1 -> 0.05038866 | S90: 0.045 | T90: =U90/U78-1 -> 0.049891523 | U90: =U89*W90 -> 137.25442 | V90: 0.36 | W90: =1+V90/100 -> 1.0036 | X90: =SUBSTITUTE(V90,",",".") -> 0.36 | Y90: =SUBSTITUTE(P90,",",".") -> 0.43 | AA90: 40634 | AB90: 81.85953 | AC90: 1004.8604 | AD90: 999.49653 | AE90: 0.005366616
A91: 41426 | B91: 0.08 | C91: =C90*(1+B91/12) -> 230.65311 | G91: -0.0068565115 | I91: 40695 | J91: 45.59679 | K91: =SUM(J80:J91) -> 535.33322 | L91: 529.7714 | M91: =(K91-L91)/L91 -> 0.010498519 | O91: 41061 | P91: 0.06 | Q91: =Q90*(1+P91/100) -> 134.77128 | R91: =Q91/Q79-1 -> 0.049549524 | S91: 0.045 | T91: =U91/U79-1 -> 0.0491577 | U91: =U90*W91 -> 137.36422 | V91: 0.08 | W91: =1+V91/100 -> 1.0008 | X91: =SUBSTITUTE(V91,",",".") -> 0.08 | Y91: =SUBSTITUTE(P91,",",".") -> 0.06 | AA91: 40664 | AB91: 86.45546 | AC91: 1013.0984 | AD91: 1006.7455 | AE91: 0.0063103316
A92: 41456 | B92: 0.083387097 | C92: =C91*(1+B92/12) -> 232.25591 | G92: -0.0011256324 | I92: 40725 | J92: 45.31848 | K92: =SUM(J81:J92) -> 539.13682 | L92: 534.72904 | M92: =(K92-L92)/L92 -> 0.0082430165 | O92: 41091 | P92: 0.6 | Q92: =Q91*(1+P92/100) -> 135.57991 | R92: =Q92/Q80-1 -> 0.053739342 | S92: 0.045 | T92: =U92/U80-1 -> 0.0519859 | U92: =U91*W92 -> 137.95489 | V92: 0.43 | W92: =1+V92/100 -> 1.0043 | X92: =SUBSTITUTE(V92,",",".") -> 0.43 | Y92: =SUBSTITUTE(P92,",",".") -> 0.6 | AA92: 40695 | AB92: 85.41487 | AC92: 1020.3825 | AD92: 1013.9767 | AE92: 0.00631753
A93: 41487 | B93: 0.085483871 | C93: =C92*(1+B93/12) -> 233.91042 | G93: -0.0022268827 | I93: 40756 | J93: 46.57088 | K93: =SUM(J82:J93) -> 543.3115 | L93: 539.69468 | M93: =(K93-L93)/L93 -> 0.0067015975 | O93: 41122 | P93: 0.48 | Q93: =Q92*(1+P93/100) -> 136.23069 | R93: =Q93/Q81-1 -> 0.057317047 | S93: 0.045 | T93: =U93/U81-1 -> 0.052405144 | U93: =U92*W93 -> 138.52051 | V93: 0.41 | W93: =1+V93/100 -> 1.0041 | X93: =SUBSTITUTE(V93,",",".") -> 0.41 | Y93: =SUBSTITUTE(P93,",",".") -> 0.48 | AA93: 40725 | AB93: 85.06801 | AC93: 1024.8917 | AD93: 1021.1838 | AE93: 0.0036309821
A94: 41518 | B94: 0.09 | C94: =C93*(1+B94/12) -> 235.66474 | G94: 0.0055224588 | I94: 40787 | J94: 44.85463 | K94: =SUM(J83:J94) -> 546.88318 | L94: 544.66607 | M94: =(K94-L94)/L94 -> 0.0040705801 | O94: 41153 | P94: 0.58 | Q94: =Q93*(1+P94/100) -> 137.02083 | R94: =Q94/Q82-1 -> 0.058053414 | S94: 0.045 | T94: =U94/U82-1 -> 0.052823886 | U94: =U93*W94 -> 139.31007 | V94: 0.57 | W94: =1+V94/100 -> 1.0057 | X94: =SUBSTITUTE(V94,",",".") -> 0.57 | Y94: =SUBSTITUTE(P94,",",".") -> 0.58 | AA94: 40756 | AB94: 87.58276 | AC94: 1030.008 | AD94: 1028.3612 | AE94: 0.0016013878
A95: 41548 | B95: 0.093548387 | C95: =C94*(1+B95/12) -> 237.50192 | G95: 0.0091330476 | I95: 40817 | J95: 46.94197 | K95: =SUM(J84:J95) -> 549.43438 | L95: 549.6412 | M95: =(K95-L95)/L95 -> -0.00037627588 | O95: 41183 | P95: 0.5 | Q95: =Q94*(1+P95/100) -> 137.70593 | R95: =Q95/Q83-1 -> 0.053024045 | S95: 0.045 | T95: =U95/U83-1 -> 0.054501192 | U95: =U94*W95 -> 140.132 | V95: 0.59 | W95: =1+V95/100 -> 1.0059 | X95: =SUBSTITUTE(V95,",",".") -> 0.59 | Y95: =SUBSTITUTE(P95,",",".") -> 0.5 | AA95: 40787 | AB95: 83.68056 | AC95: 1033.3031 | AD95: 1035.5031 | AE95: -0.0021245463
A96: 41579 | B96: 0.0955 | C96: =C95*(1+B96/12) -> 239.39204 | G96: 0.016101095 | I96: 40848 | J96: 48.4263 | K96: =SUM(J85:J96) -> 551.93919 | L96: 554.6182 | M96: =(K96-L96)/L96 -> -0.0048303609 | O96: 41214 | P96: 0.41 | Q96: =Q95*(1+P96/100) -> 138.27053 | R96: =Q96/Q84-1 -> 0.051244227 | S96: 0.045 | T96: =U96/U84-1 -> 0.055340429 | U96: =U95*W96 -> 140.97279 | V96: 0.6 | W96: =1+V96/100 -> 1.006 | X96: =SUBSTITUTE(V96,",",".") -> 0.6 | Y96: =SUBSTITUTE(P96,",",".") -> 0.41 | AA96: 40817 | AB96: 86.80232 | AC96: 1034.4305 | AD96: 1042.6043 | AE96: -0.007839876
A97: 41609 | B97: 0.1 | C97: =C96*(1+B97/12) -> 241.38697 | D97: =C97/C85-1 -> 0.086076769 | G97: 0.024238973 | I97: 40878 | J97: 62.52744 | K97: =SUM(J86:J97) -> 556.67049 | L97: 559.5952 | M97: =(K97-L97)/L97 -> -0.0052264711 | O97: 41244 | P97: 0.62 | Q97: =Q96*(1+P97/100) -> 139.12781 | R97: =Q97/Q85-1 -> 0.055756005 | S97: 0.045 | T97: =U97/U85-1 -> 0.05838569 | U97: =U96*W97 -> 142.08648 | V97: 0.79 | W97: =1+V97/100 -> 1.0079 | X97: =SUBSTITUTE(V97,",",".") -> 0.79 | Y97: =SUBSTITUTE(P97,",",".") -> 0.62 | AA97: 40848 | AB97: 89.4905 | AC97: 1035.471 | AD97: 1049.6592 | AE97: -0.013516964
A98: 41640 | B98: 0.10258065 | C98: =C97*(1+B98/12) -> 243.45044 | G98: 0.032027308 | I98: 40909 | J98: 45.59679 | K98: =SUM(J87:J98) -> 561.44818 | L98: 564.57014 | M98: =(K98-L98)/L98 -> -0.0055298073 | O98: 41275 | P98: 0.87 | Q98: =Q97*(1+P98/100) -> 140.33822 | R98: =Q98/Q86-1 -> 0.061649967 | S98: 0.045 | T98: =U98/U86-1 -> 0.061543165 | U98: =U97*W98 -> 143.30842 | V98: 0.86 | W98: =1+V98/100 -> 1.0086 | X98: =SUBSTITUTE(V98,",",".") -> 0.86 | Y98: =SUBSTITUTE(P98,",",".") -> 0.87 | AA98: 40878 | AB98: 116.11219 | AC98: 1040.674 | AD98: 1056.6617 | AE98: -0.015130413
A99: 41671 | B99: 0.10517857 | C99: =C98*(1+B99/12) -> 245.58425 | G99: 0.039834958 | I99: 40940 | J99: 41.88596 | K99: =SUM(J88:J99) -> 562.93251 | L99: 569.54077 | M99: =(K99-L99)/L99 -> -0.01160279 | O99: 41306 | P99: 0.35 | Q99: =Q98*(1+P99/100) -> 140.8294 | R99: =Q99/Q87-1 -> 0.060698668 | S99: 0.045 | T99: =U99/U87-1 -> 0.063128347 | U99: =U98*W99 -> 144.16827 | V99: 0.6 | W99: =1+V99/100 -> 1.006 | X99: =SUBSTITUTE(V99,",",".") -> 0.6 | Y99: =SUBSTITUTE(P99,",",".") -> 0.35 | AA99: 40909 | AB99: 84.72115 | AC99: 1048.1315 | AD99: 1063.6046 | AE99: -0.014547765
A100: 41699 | B100: 0.1075 | C100: =C99*(1+B100/12) -> 247.78428 | G100: 0.036830812 | I100: 40969 | J100: 49.91063 | K100: =SUM(J89:J100) -> 568.17406 | L100: 574.5046 | M100: =(K100-L100)/L100 -> -0.011019134 | O100: 41334 | P100: 0.46 | Q100: =Q99*(1+P100/100) -> 141.47722 | R100: =Q100/Q88-1 -> 0.063132677 | S100: 0.045 | T100: =U100/U88-1 -> 0.065886688 | U100: =U99*W100 -> 144.84586 | V100: 0.47 | W100: =1+V100/100 -> 1.0047 | X100: =SUBSTITUTE(V100,",",".") -> 0.47 | Y100: =SUBSTITUTE(P100,",",".") -> 0.46 | AA100: 40940 | AB100: 77.87061 | AC100: 1049.3455 | AD100: 1070.4797 | AE100: -0.019742695
...

Sheet PMC-Potencial
A1: Comércio ampliado RS | F1: potencial
A2: 37987 | B2: 21.98665
A3: 38018 | B3: 20.82702
A4: 38047 | B4: 25.04808 | I4: =SLOPE(C13:C240,D13:D240) -> 3.7882163
A5: 38078 | B5: 24.49146 | I5: =INTERCEPT(C13:C240,D13:D240) -> 228.54036
A6: 38108 | B6: 25.83664
A7: 38139 | B7: 25.18724
A8: 38169 | B8: 26.43965
A9: 38200 | B9: 26.20772
A10: 38231 | B10: 25.09447
A11: 38261 | B11: 27.41374
A12: 38292 | B12: 27.2282
A13: 38322 | B13: 36.69081 | C13: =SUM(B2:B13) -> 312.45168 | D13: 1 | F13: =$I$5+$I$4*D13 -> 232.32858
A14: 38353 | B14: 25.51194 | C14: =SUM(B3:B14) -> 315.97697 | D14: 2 | F14: =$I$5+$I$4*D14 -> 236.1168
A15: 38384 | B15: 23.05352 | C15: =SUM(B4:B15) -> 318.20347 | D15: 3 | F15: =$I$5+$I$4*D15 -> 239.90501
A16: 38412 | B16: 26.99627 | C16: =SUM(B5:B16) -> 320.15166 | D16: 4 | F16: =$I$5+$I$4*D16 -> 243.69323
A17: 38443 | B17: 25.97579 | C17: =SUM(B6:B17) -> 321.63599 | D17: 5 | F17: =$I$5+$I$4*D17 -> 247.48145
A18: 38473 | B18: 26.2541 | C18: =SUM(B7:B18) -> 322.05345 | D18: 6 | F18: =$I$5+$I$4*D18 -> 251.26966
A19: 38504 | B19: 25.79025 | C19: =SUM(B8:B19) -> 322.65646 | D19: 7 | F19: =$I$5+$I$4*D19 -> 255.05788
A20: 38534 | B20: 25.88302 | C20: =SUM(B9:B20) -> 322.09983 | D20: 8 | F20: =$I$5+$I$4*D20 -> 258.84609
A21: 38565 | B21: 25.97579 | C21: =SUM(B10:B21) -> 321.8679 | D21: 9 | F21: =$I$5+$I$4*D21 -> 262.63431
A22: 38596 | B22: 24.07399 | C22: =SUM(B11:B22) -> 320.84742 | D22: 10 | F22: =$I$5+$I$4*D22 -> 266.42253
A23: 38626 | B23: 25.65109 | C23: =SUM(B12:B23) -> 319.08477 | D23: 11 | F23: =$I$5+$I$4*D23 -> 270.21074
A24: 38657 | B24: 26.67157 | C24: =SUM(B13:B24) -> 318.52814 | D24: 12 | F24: =$I$5+$I$4*D24 -> 273.99896
... A240: 45231 | B240: 110.24613 | C240: =SUM(B229:B240) -> 1241.4896 | D240: 228 | F240: =$I$5+$I$4*D240 -> 1092.2537

Sheet Ac
B1: GDP decompostion
B2: Agregate Supply and Non-Durable productivity (AC)
B3: Yc = Ac*K^(omega)*Nc^(1-omega)*Kg^0,05 | C3: Depreciação | D3: 0.05 | E3: K inicial é I/deprec | F3: omega | G3: 0.35 | H3: =I6/B6 -> 2.572 | I3: nu | J3: 0.05 | K3: =(0.0137+0.014)/0.05 -> 0.554
B4: Componentes da função de produção | S4: Taxas de crescimento de componentes | X4: Contribuições para o crescimento | AD4: Razão investimento líquido/Capital
B5: PIB real total | C5: PIB real da Construção Civil (Yd) | D5: Yc (PIB real total menos Yd) | E5: Id/Y | F5: I/Y (Brasil) | G5: Ic/Y | H5: FBKF (Ic) | I5: K estimado | J5: IGL/Y | K5: IGC/Y | L5: Kg estimado | M5: Pessoas ocupadas (PO) - Pessoa (mil) (L) | N5: Pessoas desocupadas (PD) - Pessoa (mil) | O5: PEA | P5: Taxa de emprego (%) | Q5: Var % PO em relação a Nc | S5: PIB real (Yc) (% YoY) | T5: Capital (K) (% YoY) | U5: Capital público (Kg) (% YoY) | V5: Emprego (L) (%YoY) | X5: PIB real (Y) (% YoY) | Y5: Capital (K) (% YoY) | Z5: Capital público (Kg) (% YoY) | AA5: % PTF estimada (A(res)) | AB5: Emprego (L) (%YoY) | AD5: Razão investimento bruto / capital (It/Kt-1) | AE5: Taxa de depreciação trimestral (d) | AF5: Razão investimento líquido / capital (It/Kt-1)-d
A6: 2011 | B6: 226373.42 | C6: 12120.577 | D6: =B6-C6 -> 214252.84 | E6: 0.053542407 | F6: 0.20608964 | G6: =F6-E6 -> 0.15254724 | I6: =0.1286/$D$3*B6 -> 582232.42 | J6: 0.012653134 | K6: 0.010681842 | L6: =K3*B6 -> 125410.87 | M6: 5450
A7: 2012 | B7: =B6*(1+D20/100) -> 220627.35 | C7: 12495.152 | D7: =B7-C7 -> 208132.2 | E7: 0.063258747 | F7: 0.20716713 | G7: =F7-E7 -> 0.14390838 | H7: =G7*B7 -> 31750.125 | I7: =I6*(1-$D$3)+H7 -> 584870.93 | J7: 0.015005636 | K7: 0.012462639 | L7: =L6*(1-$D$3)+J7*B7+K7*B7 -> 125200.58 | M7: 5510.75 | N7: 281.75 | O7: =M7+N7 -> 5792.5 | P7: =M7/O7 -> 0.95135952 | Q7: 0.89651693 | S7: =D7/D6-1 -> -0.028567362 | T7: =I7/I6-1 -> 0.0045317017 | U7: =L7/L6-1 -> -0.0016768156 | V7: =(M7/M6-1)*Q7 -> 0.0099932851 | X7: =S7 -> -0.028567362 | Y7: =T7 -> 0.0045317017 | Z7: =U7 -> -0.0016768156 | AA7: =X7-Y7-AB7-Z7 -> -0.041415533 | AB7: =V7 -> 0.0099932851
A8: 2013 | B8: =B7*(1+D21/100) -> 239309.03 | C8: 13241.885 | D8: =B8-C8 -> 226067.14 | E8: 0.052445373 | F8: 0.20911922 | G8: =F8-E8 -> 0.15667385 | H8: =G8*B8 -> 37493.465 | I8: =I7*(1-$D$3)+H8 -> 593120.85 | J8: 0.012123805 | K8: 0.014233326 | L8: =L7*(1-$D$3)+J8*B8+K8*B8 -> 125248.05 | M8: 5656.25 | N8: 292.5 | O8: =M8+N8 -> 5948.75 | P8: =M8/O8 -> 0.95083001 | Q8: 0.92337682 | S8: =D8/D7-1 -> 0.086170909 | T8: =I8/I7-1 -> 0.014105538 | U8: =L8/L7-1 -> 0.00037915287 | V8: =(M8/M7-1)*Q8 -> 0.024379863 | X8: =S8 -> 0.086170909 | Y8: =T8 -> 0.014105538 | Z8: =U8 -> 0.00037915287 | AA8: =X8-Y8-AB8-Z8 -> 0.047306356 | AB8: =V8 -> 0.024379863
A9: 2014 | B9: =B8*(1+D22/100) -> 238293.3 | C9: 13045.314 | D9: =B9-C9 -> 225247.98 | E9: 0.051204673 | F9: 0.19873029 | G9: =F9-E9 -> 0.14752562 | H9: =G9*B9 -> 35154.366 | I9: =I8*(1-$D$3)+H9 -> 598619.17 | J9: 0.014234397 | K9: 0.016797374 | L9: =L8*(1-$D$3)+J9*B9+K9*B9 -> 126380.31 | M9: 5630 | N9: 302.5 | O9: =M9+N9 -> 5932.5 | P9: =M9/O9 -> 0.94900969 | Q9: 1.0362696 | S9: =D9/D8-1 -> -0.0036235086 | T9: =I9/I8-1 -> 0.0092701569 | U9: =L9/L8-1 -> 0.0090401439 | V9: =(M9/M8-1)*Q9 -> -0.0048092072 | X9: =S9 -> -0.0036235086 | Y9: =T9 -> 0.0092701569 | Z9: =U9 -> 0.0090401439 | AA9: =X9-Y9-AB9-Z9 -> -0.017124602 | AB9: =V9 -> -0.0048092072
A10: 2015 | B10: =B9*(1+D23/100) -> 228449.78 | C10: 12129.507 | D10: =B10-C10 -> 216320.28 | E10: 0.04777157 | F10: 0.17835807 | G10: =F10-E10 -> 0.1305865 | H10: =G10*B10 -> 29832.458 | I10: =I9*(1-$D$3)+H10 -> 598520.67 | J10: 0.010733026 | K10: 0.011915471 | L10: =L9*(1-$D$3)+J10*B10+K10*B10 -> 125235.34 | M10: 5645.75 | N10: 385 | O10: =M10+N10 -> 6030.75 | P10: =M10/O10 -> 0.93616051 | Q10: 0.84853726 | S10: =D10/D9-1 -> -0.039635011 | T10: =I10/I9-1 -> -0.00016454628 | U10: =L10/L9-1 -> -0.0090597281 | V10: =(M10/M9-1)*Q10 -> 0.0023737943 | X10: =S10 -> -0.039635011 | Y10: =T10 -> -0.00016454628 | Z10: =U10 -> -0.0090597281 | AA10: =X10-Y10-AB10-Z10 -> -0.032784531 | AB10: =V10 -> 0.0023737943
A11: 2016 | B11: =B10*(1+D24/100) -> 223824.14 | C11: 11438.721 | D11: =B11-C11 -> 212385.42 | E11: 0.047421591 | F11: 0.15524327 | G11: =F11-E11 -> 0.10782168 | H11: =G11*B11 -> 24133.096 | I11: =I10*(1-$D$3)+H11 -> 592727.73 | J11: 0.011131444 | K11: 0.015227132 | L11: =L10*(1-$D$3)+J11*B11+K11*B11 -> 124873.26 | M11: 5602.5 | N11: 508.75 | O11: =M11+N11 -> 6111.25 | P11: =M11/O11 -> 0.91675189 | Q11: 0.80748023 | S11: =D11/D10-1 -> -0.018189953 | T11: =I11/I10-1 -> -0.0096787599 | U11: =L11/L10-1 -> -0.002891207 | V11: =(M11/M10-1)*Q11 -> -0.006185807 | X11: =S11 -> -0.018189953 | Y11: =T11 -> -0.0096787599 | Z11: =U11 -> -0.002891207 | AA11: =X11-Y11-AB11-Z11 -> 0.0005658205 | AB11: =V11 -> -0.006185807
A12: 2017 | B12: =B11*(1+D25/100) -> 227886.62 | C12: 10774.238 | D12: =B12-C12 -> 217112.38 | E12: 0.040787195 | F12: 0.14558987 | G12: =F12-E12 -> 0.10480267 | H12: =G12*B12 -> 23883.127 | I12: =I11*(1-$D$3)+H12 -> 586974.47 | J12: 0.009883803 | K12: 0.011189453 | L12: =L11*(1-$D$3)+J12*B12+K12*B12 -> 123431.91 | M12: 5609.75 | N12: 522.75 | O12: =M12+N12 -> 6132.5 | P12: =M12/O12 -> 0.91475744 | Q12: 0.62433478 | S12: =D12/D11-1 -> 0.022256531 | T12: =I12/I11-1 -> -0.0097064128 | U12: =L12/L11-1 -> -0.011542503 | V12: =(M12/M11-1)*Q12 -> 0.00080792989 | X12: =S12 -> 0.022256531 | Y12: =T12 -> -0.0097064128 | Z12: =U12 -> -0.011542503 | AA12: =X12-Y12-AB12-Z12 -> 0.042697517 | AB12: =V12 -> 0.00080792989 | AD12: =#REF!/#REF! -> #REF! | AE12: =#REF! -> #REF! | AF12: =AD12-AE12 -> #REF!
A13: 2018 | B13: =B12*(1+D26/100) -> 231862.3 | C13: 10500.501 | D13: =B13-C13 -> 221361.8 | E13: 0.038187597 | F13: 0.15096912 | G13: =F13-E13 -> 0.11278152 | H13: =G13*B13 -> 26149.783 | I13: =I12*(1-$D$3)+H13 -> 583775.53 | J13: 0.013462629 | K13: 0.012240793 | L13: =L12*(1-$D$3)+J13*B13+K13*B13 -> 123219.97 | M13: 5558.25 | N13: 496 | O13: =M13+N13 -> 6054.25 | P13: =M13/O13 -> 0.91807408 | Q13: 0.93096387 | S13: =D13/D12-1 -> 0.01957241 | T13: =I13/I12-1 -> -0.0054498803 | U13: =L13/L12-1 -> -0.0017170679 | V13: =(M13/M12-1)*Q13 -> -0.0085466624 | X13: =S13 -> 0.01957241 | Y13: =T13 -> -0.0054498803 | Z13: =U13 -> -0.0017170679 | AA13: =X13-Y13-AB13-Z13 -> 0.035286021 | AB13: =V13 -> -0.0085466624 | AD13: =#REF!/#REF! -> #REF! | AE13: =#REF! -> #REF! | AF13: =AD13-AE13 -> #REF!
A14: 2019 | B14: =B13*(1+D27/100) -> 233802.15 | C14: 10411.42 | D14: =B14-C14 -> 223390.73 | E14: 0.041210209 | F14: 0.1547117 | G14: =F14-E14 -> 0.11350149 | H14: =G14*B14 -> 26536.891 | I14: =I13*(1-$D$3)+H14 -> 581123.65 | J14: 0.01207685 | K14: 0.013125572 | L14: =L13*(1-$D$3)+J14*B14+K14*B14 -> 122951.35 | M14: 5714.5 | N14: 505.25 | O14: =M14+N14 -> 6219.75 | P14: =M14/O14 -> 0.91876683 | Q14: 1.1752668 | S14: =D14/D13-1 -> 0.009165664 | T14: =I14/I13-1 -> -0.0045426452 | U14: =L14/L13-1 -> -0.0021799883 | V14: =(M14/M13-1)*Q14 -> 0.033038356 | X14: =S14 -> 0.009165664 | Y14: =T14 -> -0.0045426452 | Z14: =U14 -> -0.0021799883 | AA14: =X14-Y14-AB14-Z14 -> -0.017150058 | AB14: =V14 -> 0.033038356 | AD14: =#REF!/#REF! -> #REF! | AE14: =#REF! -> #REF! | AF14: =AD14-AE14 -> #REF!
A15: 2020 | B15: =B14*(1+D28/100) -> 216618.71 | C15: 9888.4284 | D15: =B15-C15 -> 206730.28 | E15: 0.040463992 | F15: 0.16561022 | G15: =F15-E15 -> 0.12514622 | H15: =G15*B15 -> 27109.013 | I15: =I14*(1-$D$3)+H15 -> 579176.48 | J15: 0.016643836 | K15: 0.026186214 | L15: =L14*(1-$D$3)+J15*B15+K15*B15 -> 126081.57 | M15: 5344.75 | N15: 549.75 | O15: =M15+N15 -> 5894.5 | P15: =M15/O15 -> 0.90673509 | Q15: 0.98320504 | S15: =D15/D14-1 -> -0.074579859 | T15: =I15/I14-1 -> -0.0033506974 | U15: =L15/L14-1 -> 0.025459033 | V15: =(M15/M14-1)*Q15 -> -0.063617125 | X15: =S15 -> -0.074579859 | Y15: =T15 -> -0.0033506974 | Z15: =U15 -> 0.025459033 | AA15: =X15-Y15-AB15-Z15 -> -0.033071069 | AB15: =V15 -> -0.063617125 | AD15: =#REF!/#REF! -> #REF! | AE15: =#REF! -> #REF! | AF15: =AD15-AE15 -> #REF!
A16: 2021 | B16: =B15*(1+D29/100) -> 237239.89 | C16: 10833.31 | D16: =B16-C16 -> 226406.58 | E16: 0.035541589 | F16: 0.17914033 | G16: =F16-E16 -> 0.14359874 | H16: =G16*B16 -> 34067.349 | I16: =I15*(1-$D$3)+H16 -> 584285 | J16: 0.019637733 | K16: 0.012189139 | L16: =L15*(1-$D$3)+J16*B16+K16*B16 -> 127328.1 | M16: 5523.75 | N16: 527.75 | O16: =M16+N16 -> 6051.5 | P16: =M16/O16 -> 0.91279022 | Q16: 0.96365159 | S16: =D16/D15-1 -> 0.095178637 | T16: =I16/I15-1 -> 0.0088203255 | U16: =L16/L15-1 -> 0.0098866543 | V16: =(M16/M15-1)*Q16 -> 0.032273471 | X16: =S16 -> 0.095178637 | Y16: =T16 -> 0.0088203255 | Z16: =U16 -> 0.0098866543 | AA16: =X16-Y16-AB16-Z16 -> 0.044198186 | AB16: =V16 -> 0.032273471 | AD16: =#REF!/#REF! -> #REF! | AE16: =#REF! -> #REF! | AF16: =AD16-AE16 -> #REF!
A17: 2022 | B17: =B16*(1-0.052) -> 224903.42 | C17: =C16*1.058 -> 11461.642 | D17: =B17-C17 -> 213441.78 | M17: 5842.75 | N17: 378.75 | O17: =M17+N17 -> 6221.5 | P17: =M17/O17 -> 0.9391224 | Q17: 0.93174792 | V17: =(M17/M16-1)*Q17 -> 0.053809022 | X17: =S17 -> 0 | AB17: =V17 -> 0.053809022 | AD17: =#REF!/#REF! -> #REF! | AE17: =#REF! -> #REF! | AF17: =AD17-AE17 -> #REF!
A18: Ano | B18: Ac
A19: 2011 | B19: 100 | D19: Crescimento Y total 2011- 2020 %
A20: 2012 | B20: =B19*(1+AA7) -> 95.858447 | D20: -2.538312
A21: 2013 | B21: =B20*(1+AA8) -> 100.39316 | D21: 8.4675239
A22: 2014 | B22: =B21*(1+AA9) -> 98.673968 | D22: -0.42444166
A23: 2015 | B23: =B22*(1+AA10) -> 95.438988 | D23: -4.1308395
A24: 2016 | B24: =B23*(1+AA11) -> 95.492989 | D24: -2.0247959
A25: 2017 | B25: =B24*(1+AA12) -> 99.570303 | D25: 1.8150323
A26: 2018 | B26: =B25*(1+AA13) -> 103.08374 | D26: 1.7445847
A27: 2019 | B27: =B26*(1+AA14) -> 101.31585 | D27: 0.83663755
A28: 2020 | B28: =B27*(1+AA15) -> 97.965227 | D28: -7.3495648
A29: 2021 | B29: =B28*(1+AA16) -> 102.29511 | D29: 9.5195786
B36: Yd | C36: Yc | D36: IC
B37: 12120.577 | C37: 214252.84 | D37: =G6*B6 -> 34532.639
B38: 12495.152 | C38: 208132.2 | D38: =G7*B7 -> 31750.125
B39: 13241.885 | C39: 226067.14 | D39: =G8*B8 -> 37493.465
B40: 13045.314 | C40: 225247.98 | D40: =G9*B9 -> 35154.366
B41: 12129.507 | C41: 216320.28 | D41: =G10*B10 -> 29832.458
B42: 11438.721 | C42: 212385.42 | D42: =G11*B11 -> 24133.096
B43: 10774.238 | C43: 217112.38 | D43: =G12*B12 -> 23883.127
B44: 10500.501 | C44: 221361.8 | D44: =G13*B13 -> 26149.783
B45: 10411.42 | C45: 223390.73 | D45: =G14*B14 -> 26536.891
B46: 9888.4284 | C46: 206730.28 | D46: =G15*B15 -> 27109.013
B47: 10833.31 | C47: 226406.58 | D47: =G16*B16 -> 34067.349
B50: =SUBSTITUTE(B37,",",".") -> 12120.5774538739 | C50: =SUBSTITUTE(C37,",",".") -> 214252.837991112 | D50: =SUBSTITUTE(D37,",",".") -> 34532.6387123679
B51: =SUBSTITUTE(B38,",",".") -> 12495.1521258896 | C51: =SUBSTITUTE(C38,",",".") -> 208132.199679521 | D51: =SUBSTITUTE(D38,",",".") -> 31750.1249153153
B52: =SUBSTITUTE(B39,",",".") -> 13241.885057724 | C52: =SUBSTITUTE(C39,",",".") -> 226067.140545843 | D52: =SUBSTITUTE(D39,",",".") -> 37493.4654037566
B53: =SUBSTITUTE(B40,",",".") -> 13045.314084959 | C53: =SUBSTITUTE(C40,",",".") -> 225247.984321443 | D53: =SUBSTITUTE(D40,",",".") -> 35154.3656941288
B54: =SUBSTITUTE(B41,",",".") -> 12129.5066575035 | C54: =SUBSTITUTE(C41,",",".") -> 216320.277980822 | D54: =SUBSTITUTE(D41,",",".") -> 29832.4579674998
B55: =SUBSTITUTE(B42,",",".") -> 11438.7205975324 | C55: =SUBSTITUTE(C42,",",".") -> 212385.422190798 | D55: =SUBSTITUTE(D42,",",".") -> 24133.0956470434
B56: =SUBSTITUTE(B43,",",".") -> 10774.2382180593 | C56: =SUBSTITUTE(C43,",",".") -> 217112.384963155 | D56: =SUBSTITUTE(D43,",",".") -> 23883.1265364085
B57: =SUBSTITUTE(B44,",",".") -> 10500.5006275063 | C57: =SUBSTITUTE(C44,",",".") -> 221361.797675915 | D57: =SUBSTITUTE(D44,",",".") -> 26149.7829864365
B58: =SUBSTITUTE(B45,",",".") -> 10411.4198312891 | C58: =SUBSTITUTE(C45,",",".") -> 223390.725528341 | D58: =SUBSTITUTE(D45,",",".") -> 26536.8914681371
B59: =SUBSTITUTE(B46,",",".") -> 9888.42836808254 | C59: =SUBSTITUTE(C46,",",".") -> 206730.276816509 | D59: =SUBSTITUTE(D46,",",".") -> 27109.0128215455
B60: =SUBSTITUTE(B47,",",".") -> 10833.310129237 | C60: =SUBSTITUTE(C47,",",".") -> 226406.582850975 | D60: =SUBSTITUTE(D47,",",".") -> 34067.3488717786
B61: =SUBSTITUTE(B48,",",".") | C61: =SUBSTITUTE(C48,",",".") | D61: =SUBSTITUTE(D48,",",".")
B62: =SUBSTITUTE(B49,",",".") | C62: =SUBSTITUTE(C49,",",".") | D62: =SUBSTITUTE(D49,",",".")

Sheet Ad
B1: GDP decompostion
B2: Agregate Supply and Durable productivity (AD)
B3: Yd = Ad*Nd
B4: Componentes da função de produção | I4: Taxas de crescimento de componentes | L4: Contribuições para o crescimento
B5: PIB real da Construção Civil (Yd) | C5: Pessoas ocupadas (PO) - Pessoa (mil) (L) | D5: Pessoas desocupadas (PD) - Pessoa (mil) | E5: PEA | F5: Taxa de emprego (%) | G5: Var % PO em relação a Nd | I5: PIB real (Y) (% YoY) | J5: Emprego (L) (%YoY) | L5: PIB real (Y) (% YoY) | M5: PTF estimada (A(res)) | N5: Emprego (L)
A6: 2011 | B6: 12120.577 | C6: 5450
A7: 2012 | B7: =B6*(1+D21/100) -> 12495.152 | C7: 5510.75 | D7: 281.75 | E7: =C7+D7 -> 5792.5 | F7: =C7/E7 -> 0.95135952 | G7: 0.10348307 | I7: =B7/B6-1 -> 0.030904029 | J7: =(C7/C6-1)*G7 -> 0.0011535039 | L7: =I7 -> 0.030904029 | M7: =L7-N7 -> 0.029750525 | N7: =J7 -> 0.0011535039
A8: 2013 | B8: =B7*(1+D22/100) -> 13241.885 | C8: 5656.25 | D8: 292.5 | E8: =C8+D8 -> 5948.75 | F8: =C8/E8 -> 0.95083001 | G8: 0.076623175 | I8: =B8/B7-1 -> 0.059761812 | J8: =(C8/C7-1)*G8 -> 0.0020230771 | L8: =I8 -> 0.059761812 | M8: =L8-N8 -> 0.057738735 | N8: =J8 -> 0.0020230771
A9: 2014 | B9: =B8*(1+D23/100) -> 13045.314 | C9: 5630 | D9: 302.5 | E9: =C9+D9 -> 5932.5 | F9: =C9/E9 -> 0.94900969 | G9: -0.03626965 | I9: =B9/B8-1 -> -0.014844637 | J9: =(C9/C8-1)*G9 -> 0.00016832324 | L9: =I9 -> -0.014844637 | M9: =L9-N9 -> -0.01501296 | N9: =J9 -> 0.00016832324
A10: 2015 | B10: =B9*(1+D24/100) -> 12129.507 | C10: 5645.75 | D10: 385 | E10: =C10+D10 -> 6030.75 | F10: =C10/E10 -> 0.93616051 | G10: 0.15146274 | I10: =B10/B9-1 -> -0.070202022 | J10: =(C10/C9-1)*G10 -> 0.00042371903 | L10: =I10 -> -0.070202022 | M10: =L10-N10 -> -0.070625741 | N10: =J10 -> 0.00042371903
A11: 2016 | B11: =B10*(1+D25/100) -> 11438.721 | C11: 5602.5 | D11: 508.75 | E11: =C11+D11 -> 6111.25 | F11: =C11/E11 -> 0.91675189 | G11: 0.19251977 | I11: =B11/B10-1 -> -0.056950879 | J11: =(C11/C10-1)*G11 -> -0.0014748226 | L11: =I11 -> -0.056950879 | M11: =L11-N11 -> -0.055476056 | N11: =J11 -> -0.0014748226
A12: 2017 | B12: =B11*(1+D26/100) -> 10774.238 | C12: 5609.75 | D12: 522.75 | E12: =C12+D12 -> 6132.5 | F12: =C12/E12 -> 0.91475744 | G12: 0.37566522 | I12: =B12/B11-1 -> -0.058090621 | J12: =(C12/C11-1)*G12 -> 0.00048613526 | L12: =I12 -> -0.058090621 | M12: =L12-N12 -> -0.058576756 | N12: =J12 -> 0.00048613526
A13: 2018 | B13: =B12*(1+D27/100) -> 10500.501 | C13: 5558.25 | D13: 496 | E13: =C13+D13 -> 6054.25 | F13: =C13/E13 -> 0.91807408 | G13: 0.069036127 | I13: =B13/B12-1 -> -0.025406677 | J13: =(C13/C12-1)*G13 -> -0.00063378235 | L13: =I13 -> -0.025406677 | M13: =L13-N13 -> -0.024772895 | N13: =J13 -> -0.00063378235
A14: 2019 | B14: =B13*(1+D28/100) -> 10411.42 | C14: 5714.5 | D14: 505.25 | E14: =C14+D14 -> 6219.75 | F14: =C14/E14 -> 0.91876683 | G14: -0.17526682 | I14: =B14/B13-1 -> -0.0084834809 | J14: =(C14/C13-1)*G14 -> -0.0049269896 | L14: =I14 -> -0.0084834809 | M14: =L14-N14 -> -0.0035564912 | N14: =J14 -> -0.0049269896
A15: 2020 | B15: =B14*(1+D29/100) -> 9888.4284 | C15: 5344.75 | D15: 549.75 | E15: =C15+D15 -> 5894.5 | F15: =C15/E15 -> 0.90673509 | G15: 0.016794962 | I15: =B15/B14-1 -> -0.050232482 | J15: =(C15/C14-1)*G15 -> -0.0010866982 | L15: =I15 -> -0.050232482 | M15: =L15-N15 -> -0.049145784 | N15: =J15 -> -0.0010866982
A16: 2021 | B16: =B15*(1+D30/100) -> 10833.31 | C16: 5523.75 | D16: 527.75 | E16: =C16+D16 -> 6051.5 | F16: =C16/E16 -> 0.91279022 | G16: 0.036348408 | I16: =B16/B15-1 -> 0.095554291 | J16: =(C16/C15-1)*G16 -> 0.0012173376 | L16: =I16 -> 0.095554291 | M16: =L16-N16 -> 0.094336953 | N16: =J16 -> 0.0012173376
A17: 2022 | B17: =B16*1.058 -> 11461.642 | C17: 5842.75 | D17: 378.75 | E17: =C17+D17 -> 6221.5 | F17: =C17/E17 -> 0.9391224 | G17: 0.068252078 | I17: =B17/B16-1 -> 0.058 | J17: =(C17/C16-1)*G17 -> 0.0039416 | L17: =I17 -> 0.058 | M17: =L17-N17 -> 0.0540584 | N17: =J17 -> 0.0039416
C18: 5903 | D18: 332.66667 | E18: =C18+D18 -> 6235.6667 | F18: =C18/E18 -> 0.94665099 | G18: -0.034111311
A19: Ano | B19: Ad
A20: 2011 | B20: 100 | D20: Crescimento 2012-2020
A21: 2012 | B21: =B20*(1+M7) -> 102.97505 | D21: 3.0904029
A22: 2013 | B22: =B21*(1+M8) -> 108.9207 | D22: 5.9761812
A23: 2014 | B23: =B22*(1+M9) -> 107.28548 | D23: -1.4844637
A24: 2015 | B24: =B23*(1+M10) -> 99.708363 | D24: -7.0202022
A25: 2016 | B25: =B24*(1+M11) -> 94.176936 | D25: -5.6950879
A26: 2017 | B26: =B25*(1+M12) -> 88.660357 | D26: -5.8090621
A27: 2018 | B27: =B26*(1+M13) -> 86.463983 | D27: -2.5406677
A28: 2019 | B28: =B27*(1+M14) -> 86.156475 | D28: -0.84834809
A29: 2020 | B29: =B28*(1+M15) -> 81.922247 | D29: -5.0232482
A30: 2021 | B30: =B29*(1+M16) -> 89.650543 | D30: 9.5554291
A31: 2022

Sheet Employment
A1: Ano | B1: Trimestre | C1: PO | D1: Desocupadas | E1: Total | F1: Emprego % | H1: Variação | I1: Proporção | J1: PO CC | K1: PO NCC
A2: 2012 | B2: 1 | C2: 5439 | D2: 307 | E2: =C2+D2 -> 5746 | F2: =C2/E2 -> 0.94657153 | I2: 0.11453404
A3: 2012 | B3: 2 | C3: 5515 | D3: 295 | E3: =C3+D3 -> 5810 | F3: =C3/E3 -> 0.94922547 | G3: =F3-F2 -> 0.0026539453 | H3: =(C3-C2)/C2 -> 0.013973157 | I3: 0.26775573 | J3: =I3*H3 -> 0.0037413928 | K3: =(1-I3)*H3 -> 0.010231764
A4: 2012 | B4: 3 | C4: 5509 | D4: 269 | E4: =C4+D4 -> 5778 | F4: =C4/E4 -> 0.9534441 | G4: =F4-F3 -> 0.004218625 | H4: =(C4-C3)/C3 -> -0.001087942 | I4: 0.15725456 | J4: =I4*H4 -> -0.00017108384 | K4: =(1-I4)*H4 -> -0.00091685814
A5: 2012 | B5: 4 | C5: 5580 | D5: 256 | E5: =C5+D5 -> 5836 | F5: =C5/E5 -> 0.95613434 | G5: =F5-F4 -> 0.0026902403 | H5: =(C5-C4)/C4 -> 0.012888001 | I5: -1.3857664 | J5: =I5*H5 -> -0.01785976 | K5: =(1-I5)*H5 -> 0.030747761
A6: 2013 | B6: 1 | C6: 5593 | D6: 320 | E6: =C6+D6 -> 5913 | F6: =C6/E6 -> 0.94588196 | G6: =F6-F5 -> -0.010252384 | H6: =(C6-C5)/C5 -> 0.0023297491 | I6: 0.089044363 | J6: =I6*H6 -> 0.00020745103 | K6: =(1-I6)*H6 -> 0.0021222981
A7: 2013 | B7: 2 | C7: 5647 | D7: 274 | E7: =C7+D7 -> 5921 | F7: =C7/E7 -> 0.95372403 | G7: =F7-F6 -> 0.0078420781 | H7: =(C7-C6)/C6 -> 0.0096549258 | I7: 0.20512062 | J7: =I7*H7 -> 0.0019804243 | K7: =(1-I7)*H7 -> 0.0076745015
A8: 2013 | B8: 3 | C8: 5680 | D8: 293 | E8: =C8+D8 -> 5973 | F8: =C8/E8 -> 0.95094592 | G8: =F8-F7 -> -0.0027781098 | H8: =(C8-C7)/C7 -> 0.0058438109 | I8: 0.10417301 | J8: =I8*H8 -> 0.00060876738 | K8: =(1-I8)*H8 -> 0.0052350435
A9: 2013 | B9: 4 | C9: 5705 | D9: 283 | E9: =C9+D9 -> 5988 | F9: =C9/E9 -> 0.95273881 | G9: =F9-F8 -> 0.0017928876 | H9: =(C9-C8)/C8 -> 0.0044014085 | I9: 0.4221265 | J9: =I9*H9 -> 0.0018579512 | K9: =(1-I9)*H9 -> 0.0025434573
A10: 2014 | B10: 1 | C10: 5634 | D10: 324 | E10: =C10+D10 -> 5958 | F10: =C10/E10 -> 0.94561934 | G10: =F10-F9 -> -0.0071194756 | H10: =(C10-C9)/C9 -> -0.012445223 | I10: 0.13621087 | J10: =I10*H10 -> -0.0016951747 | K10: =(1-I10)*H10 -> -0.010750049
A11: 2014 | B11: 2 | C11: 5622 | D11: 298 | E11: =C11+D11 -> 5920 | F11: =C11/E11 -> 0.94966216 | G11: =F11-F10 -> 0.0040428268 | H11: =(C11-C10)/C10 -> -0.0021299255 | I11: 2 | J11: =I11*H11 -> -0.0042598509 | K11: =(1-I11)*H11 -> 0.0021299255
A12: 2014 | B12: 3 | C12: 5608 | D12: 315 | E12: =C12+D12 -> 5923 | F12: =C12/E12 -> 0.94681749 | G12: =F12-F11 -> -0.002844671 | H12: =(C12-C11)/C11 -> -0.002490217 | I12: 0.31751412 | J12: =I12*H12 -> -0.00079067907 | K12: =(1-I12)*H12 -> -0.0016995379
A13: 2014 | B13: 4 | C13: 5656 | D13: 273 | E13: =C13+D13 -> 5929 | F13: =C13/E13 -> 0.95395514 | G13: =F13-F12 -> 0.0071376446 | H13: =(C13-C12)/C12 -> 0.0085592011 | I13: 0.26347938 | J13: =I13*H13 -> 0.002255173 | K13: =(1-I13)*H13 -> 0.0063040281
A14: 2015 | B14: 1 | C14: 5677 | D14: 350 | E14: =C14+D14 -> 6027 | F14: =C14/E14 -> 0.94192799 | G14: =F14-F13 -> -0.012027145 | H14: =(C14-C13)/C13 -> 0.0037128713 | I14: -0.043084255 | J14: =I14*H14 -> -0.00015996629 | K14: =(1-I14)*H14 -> 0.0038728376
... A33: 2019 | B33: 4 | C33: 5819 | D33: 455 | E33: =C33+D33 -> 6274 | F33: =C33/E33 -> 0.92747848 | G33: =F33-F32 -> 0.016821689 | H33: =(C33-C32)/C32 -> 0.028637087 | I33: -0.83326386 | J33: =I33*H33 -> -0.023862249 | K33: =(1-I33)*H33 -> 0.052499336
A34: 2020 | B34: 1 | C34: 5668 | D34: 529 | E34: =C34+D34 -> 6197 | F34: =C34/E34 -> 0.91463611 | G34: =F34-F33 -> -0.012842368 | H34: =(C34-C33)/C33 -> -0.025949476
A35: 2020 | B35: 2 | C35: 5244 | D35: 562 | E35: =C35+D35 -> 5806 | F35: =C35/E35 -> 0.90320358 | G35: =F35-F34 -> -0.011432532 | H35: =(C35-C34)/C34 -> -0.074805928
A36: 2020 | B36: 3 | C36: 5111 | D36: 601 | E36: =C36+D36 -> 5712 | F36: =C36/E36 -> 0.89478291 | G36: =F36-F35 -> -0.0084206693 | H36: =(C36-C35)/C35 -> -0.025362319
A37: 2020 | B37: 4 | C37: 5356 | D37: 507 | E37: =C37+D37 -> 5863 | F37: =C37/E37 -> 0.9135255 | G37: =F37-F36 -> 0.018742586 | H37: =(C37-C36)/C36 -> 0.047935825
A38: 2021 | B38: 1 | C38: 5359 | D38: 566 | E38: =C38+D38 -> 5925 | F38: =C38/E38 -> 0.90447257 | G38: =F38-F37 -> -0.0090529251 | H38: =(C38-C37)/C37 -> 0.00056011949
A39: 2021 | B39: 2 | C39: 5490 | D39: 533 | E39: =C39+D39 -> 6023 | F39: =C39/E39 -> 0.91150589 | G39: =F39-F38 -> 0.0070333202 | H39: =(C39-C38)/C38 -> 0.024444859
A40: 2021 | B40: 3 | C40: 5573 | D40: 512 | E40: =C40+D40 -> 6085 | F40: =C40/E40 -> 0.91585867 | G40: =F40-F39 -> 0.0043527748 | H40: =(C40-C39)/C39 -> 0.015118397
A41: 2021 | B41: 4 | C41: 5673 | D41: 500 | E41: =C41+D41 -> 6173 | F41: =C41/E41 -> 0.91900211 | G41: =F41-F40 -> 0.0031434371 | H41: =(C41-C40)/C40 -> 0.017943657
A42: 2022 | B42: 1 | C42: 5740 | D42: 463 | E42: =C42+D42 -> 6203 | F42: =C42/E42 -> 0.9253587 | G42: =F42-F41 -> 0.0063565915 | H42: =(C42-C41)/C41 -> 0.01181033
A43: 2022 | B43: 2 | C43: 5795 | D43: 387 | E43: =C43+D43 -> 6182 | F43: =C43/E43 -> 0.9373989 | G43: =F43-F42 -> 0.012040203 | H43: =(C43-C42)/C42 -> 0.0095818815
A44: 2022 | B44: 3 | C44: 5885 | D44: 376 | E44: =C44+D44 -> 6261 | F44: =C44/E44 -> 0.9399457 | G44: =F44-F43 -> 0.0025467955 | H44: =(C44-C43)/C43 -> 0.01553063
A45: 2022 | B45: 4 | C45: 5951 | D45: 289 | E45: =C45+D45 -> 6240 | F45: =C45/E45 -> 0.9536859 | G45: =F45-F44 -> 0.013740202 | H45: =(C45-C44)/C44 -> 0.011214953
... A48: 2023 | B48: 3 | C48: 5843 | D48: 331 | E48: =C48+D48 -> 6174 | F48: =C48/E48 -> 0.94638808 | G48: =F48-F47 -> -0.00098873486 | H48: =(C48-C47)/C47 -> -0.016495539
B50: CC | C50: OUTROS
A51: 2020 | B51: -696 | C51: -41441
A52: 2021 | B52: 5251 | C52: 144463
A53: 2022 | B53: 6822 | C53: 99953
A54: 2023 | B54: -1596 | C54: 46788

Sheet Durable GDP
A1: SÉRIE COM AJUSTE SAZONAL DO ÍNDICE DE VOLUME TRIMESTRAL | E1: PIB nominal CC 2002 | F1: 4252.7189 | G1: 400
A2: Período | B2: Construção Civil | C2: PIB total | F2: PIB real CC
A3: 2003.I | B3: 99.375583 | C3: 98.773053 | F3: =B3*$F$1/100 -> 4226.1642
A4: 2003.II | B4: 94.910657 | C4: 108.30167 | F4: =B4*$F$1/100 -> 4036.2835
A5: 2003.III | B5: 92.417748 | C5: 98.448941 | F5: =B5*$F$1/100 -> 3930.2671
A6: 2003.IV | B6: 92.630648 | C6: 102.27415 | F6: =B6*$F$1/100 -> 3939.3211
A7: 2004.I | B7: 96.541742 | C7: 105.94984 | F7: =B7*$F$1/100 -> 4105.6489
A8: 2004.II | B8: 99.279795 | C8: 104.50011 | F8: =B8*$F$1/100 -> 4222.0906
A9: 2004.III | B9: 102.99613 | C9: 105.1108 | F9: =B9*$F$1/100 -> 4380.136
A10: 2004.IV | B10: 100.56434 | C10: 105.70897 | F10: =B10*$F$1/100 -> 4276.7188
A11: 2005.I | B11: 102.25694 | C11: 103.41124 | F11: =B11*$F$1/100 -> 4348.7
A12: 2005.II | B12: 105.44485 | C12: 101.01189 | F12: =B12*$F$1/100 -> 4484.2731
A13: 2005.III | B13: 103.87364 | C13: 103.107 | F13: =B13*$F$1/100 -> 4417.4541
A14: 2005.IV | B14: 104.52091 | C14: 102.17531 | F14: =B14*$F$1/100 -> 4444.9806
... A83: 2023.I | B83: 141.55769 | C83: 131.8407 | F83: =B83*$F$1/100 -> 6020.0508
